{
  "schema": "china.article.v2",
  "doc_version": "2026-05-phase1",
  "category_code": "12",
  "category_dir": "12-myth",
  "article_slug": "09-cangjie-creates-writing",
  "article": {
    "local_id": "myth-009",
    "category_code": "12",
    "title_pinyin": "cāng jié zào zì wèi shén me jiě shì wén zì qǐ yuán",
    "title_i18n": {
      "zh": "仓颉造字为什么解释文字起源？",
      "en": "Why Does Cangjie Creating Characters Explain Writing Origins?",
      "vi": "Vì sao Thương Hiệt tạo chữ giải thích nguồn gốc chữ viết?",
      "th": "ทำไมชางเจี๋ยสร้างอักษรจึงอธิบายต้นกำเนิดตัวเขียน?",
      "id": "Mengapa Cangjie mencipta aksara menjelaskan asal tulisan?"
    }
  },
  "content_policy": {
    "sentence_target": 120,
    "sentence_hard_max": 120,
    "update_mode": "append_only_infinite",
    "phase": "phase1",
    "risk_controls": [
      "sea_market_safe",
      "no_politics",
      "no_ethnic_conflict",
      "no_religious_dispute",
      "no_territorial_dispute",
      "no_adult_sexual_content"
    ]
  },
  "source_story_zh": [
    "仓颉造字解释文字起源，是因为传说把观察鸟兽足迹、辨认万物和创造符号连成一幅画面。",
    "它把仓颉造字和文字起源放回天地起源、自然变化和人类生活想象之中。",
    "神话并不等同于事实记录，而是用故事表达古人面对世界时的理解方式。",
    "人物、神力、灾害和修复行动常被放在同一段叙事里，形成强烈画面。",
    "如果只记住名字，人们容易忽略故事背后的自然观察和生活愿望。",
    "观察足迹也说明，神话常用夸张形象回答起源、秩序和生存问题。",
    "这些故事通过口头讲述、图像、节日和儿童读物不断流传。",
    "当代理解神话时，可以同时看到想象力、象征意义和文化记忆。",
    "把角色、情节和解释功能连起来，神话就不只是奇异故事。",
    "因此，观察足迹不仅是传说内容，也帮助人们理解仓颉造字和文字起源。",
    "创造符号是理解仓颉造字和文字起源的重要神话画面。",
    "它把仓颉造字和文字起源放回天地起源、自然变化和人类生活想象之中。",
    "神话并不等同于事实记录，而是用故事表达古人面对世界时的理解方式。",
    "人物、神力、灾害和修复行动常被放在同一段叙事里，形成强烈画面。",
    "如果只记住名字，人们容易忽略故事背后的自然观察和生活愿望。",
    "创造符号也说明，神话常用夸张形象回答起源、秩序和生存问题。",
    "这些故事通过口头讲述、图像、节日和儿童读物不断流传。",
    "当代理解神话时，可以同时看到想象力、象征意义和文化记忆。",
    "把角色、情节和解释功能连起来，神话就不只是奇异故事。",
    "因此，创造符号不仅是传说内容，也帮助人们理解仓颉造字和文字起源。",
    "文字起源是理解仓颉造字和文字起源的重要神话画面。",
    "它把仓颉造字和文字起源放回天地起源、自然变化和人类生活想象之中。",
    "神话并不等同于事实记录，而是用故事表达古人面对世界时的理解方式。",
    "人物、神力、灾害和修复行动常被放在同一段叙事里，形成强烈画面。",
    "如果只记住名字，人们容易忽略故事背后的自然观察和生活愿望。",
    "文字起源也说明，神话常用夸张形象回答起源、秩序和生存问题。",
    "这些故事通过口头讲述、图像、节日和儿童读物不断流传。",
    "当代理解神话时，可以同时看到想象力、象征意义和文化记忆。",
    "把角色、情节和解释功能连起来，神话就不只是奇异故事。",
    "因此，文字起源不仅是传说内容，也帮助人们理解仓颉造字和文字起源。",
    "仓颉形象是理解仓颉造字和文字起源的重要神话画面。",
    "它把仓颉造字和文字起源放回天地起源、自然变化和人类生活想象之中。",
    "神话并不等同于事实记录，而是用故事表达古人面对世界时的理解方式。",
    "人物、神力、灾害和修复行动常被放在同一段叙事里，形成强烈画面。",
    "如果只记住名字，人们容易忽略故事背后的自然观察和生活愿望。",
    "仓颉形象也说明，神话常用夸张形象回答起源、秩序和生存问题。",
    "这些故事通过口头讲述、图像、节日和儿童读物不断流传。",
    "当代理解神话时，可以同时看到想象力、象征意义和文化记忆。",
    "把角色、情节和解释功能连起来，神话就不只是奇异故事。",
    "因此，仓颉形象不仅是传说内容，也帮助人们理解仓颉造字和文字起源。",
    "四目传说是理解仓颉造字和文字起源的重要神话画面。",
    "它把仓颉造字和文字起源放回天地起源、自然变化和人类生活想象之中。",
    "神话并不等同于事实记录，而是用故事表达古人面对世界时的理解方式。",
    "人物、神力、灾害和修复行动常被放在同一段叙事里，形成强烈画面。",
    "如果只记住名字，人们容易忽略故事背后的自然观察和生活愿望。",
    "四目传说也说明，神话常用夸张形象回答起源、秩序和生存问题。",
    "这些故事通过口头讲述、图像、节日和儿童读物不断流传。",
    "当代理解神话时，可以同时看到想象力、象征意义和文化记忆。",
    "把角色、情节和解释功能连起来，神话就不只是奇异故事。",
    "因此，四目传说不仅是传说内容，也帮助人们理解仓颉造字和文字起源。",
    "万物分类是理解仓颉造字和文字起源的重要神话画面。",
    "它把仓颉造字和文字起源放回天地起源、自然变化和人类生活想象之中。",
    "神话并不等同于事实记录，而是用故事表达古人面对世界时的理解方式。",
    "人物、神力、灾害和修复行动常被放在同一段叙事里，形成强烈画面。",
    "如果只记住名字，人们容易忽略故事背后的自然观察和生活愿望。",
    "万物分类也说明，神话常用夸张形象回答起源、秩序和生存问题。",
    "这些故事通过口头讲述、图像、节日和儿童读物不断流传。",
    "当代理解神话时，可以同时看到想象力、象征意义和文化记忆。",
    "把角色、情节和解释功能连起来，神话就不只是奇异故事。",
    "因此，万物分类不仅是传说内容，也帮助人们理解仓颉造字和文字起源。",
    "记录能力是理解仓颉造字和文字起源的重要神话画面。",
    "它把仓颉造字和文字起源放回天地起源、自然变化和人类生活想象之中。",
    "神话并不等同于事实记录，而是用故事表达古人面对世界时的理解方式。",
    "人物、神力、灾害和修复行动常被放在同一段叙事里，形成强烈画面。",
    "如果只记住名字，人们容易忽略故事背后的自然观察和生活愿望。",
    "记录能力也说明，神话常用夸张形象回答起源、秩序和生存问题。",
    "这些故事通过口头讲述、图像、节日和儿童读物不断流传。",
    "当代理解神话时，可以同时看到想象力、象征意义和文化记忆。",
    "把角色、情节和解释功能连起来，神话就不只是奇异故事。",
    "因此，记录能力不仅是传说内容，也帮助人们理解仓颉造字和文字起源。",
    "神奇反应是理解仓颉造字和文字起源的重要神话画面。",
    "它把仓颉造字和文字起源放回天地起源、自然变化和人类生活想象之中。",
    "神话并不等同于事实记录，而是用故事表达古人面对世界时的理解方式。",
    "人物、神力、灾害和修复行动常被放在同一段叙事里，形成强烈画面。",
    "如果只记住名字，人们容易忽略故事背后的自然观察和生活愿望。",
    "神奇反应也说明，神话常用夸张形象回答起源、秩序和生存问题。",
    "这些故事通过口头讲述、图像、节日和儿童读物不断流传。",
    "当代理解神话时，可以同时看到想象力、象征意义和文化记忆。",
    "把角色、情节和解释功能连起来，神话就不只是奇异故事。",
    "因此，神奇反应不仅是传说内容，也帮助人们理解仓颉造字和文字起源。",
    "黄帝关联是理解仓颉造字和文字起源的重要神话画面。",
    "它把仓颉造字和文字起源放回天地起源、自然变化和人类生活想象之中。",
    "神话并不等同于事实记录，而是用故事表达古人面对世界时的理解方式。",
    "人物、神力、灾害和修复行动常被放在同一段叙事里，形成强烈画面。",
    "如果只记住名字，人们容易忽略故事背后的自然观察和生活愿望。",
    "黄帝关联也说明，神话常用夸张形象回答起源、秩序和生存问题。",
    "这些故事通过口头讲述、图像、节日和儿童读物不断流传。",
    "当代理解神话时，可以同时看到想象力、象征意义和文化记忆。",
    "把角色、情节和解释功能连起来，神话就不只是奇异故事。",
    "因此，黄帝关联不仅是传说内容，也帮助人们理解仓颉造字和文字起源。",
    "汉字记忆是理解仓颉造字和文字起源的重要神话画面。",
    "它把仓颉造字和文字起源放回天地起源、自然变化和人类生活想象之中。",
    "神话并不等同于事实记录，而是用故事表达古人面对世界时的理解方式。",
    "人物、神力、灾害和修复行动常被放在同一段叙事里，形成强烈画面。",
    "如果只记住名字，人们容易忽略故事背后的自然观察和生活愿望。",
    "汉字记忆也说明，神话常用夸张形象回答起源、秩序和生存问题。",
    "这些故事通过口头讲述、图像、节日和儿童读物不断流传。",
    "当代理解神话时，可以同时看到想象力、象征意义和文化记忆。",
    "把角色、情节和解释功能连起来，神话就不只是奇异故事。",
    "因此，汉字记忆不仅是传说内容，也帮助人们理解仓颉造字和文字起源。",
    "文化解释是理解仓颉造字和文字起源的重要神话画面。",
    "它把仓颉造字和文字起源放回天地起源、自然变化和人类生活想象之中。",
    "神话并不等同于事实记录，而是用故事表达古人面对世界时的理解方式。",
    "人物、神力、灾害和修复行动常被放在同一段叙事里，形成强烈画面。",
    "如果只记住名字，人们容易忽略故事背后的自然观察和生活愿望。",
    "文化解释也说明，神话常用夸张形象回答起源、秩序和生存问题。",
    "这些故事通过口头讲述、图像、节日和儿童读物不断流传。",
    "当代理解神话时，可以同时看到想象力、象征意义和文化记忆。",
    "把角色、情节和解释功能连起来，神话就不只是奇异故事。",
    "因此，文化解释不仅是传说内容，也帮助人们理解仓颉造字和文字起源。",
    "学习趣味是理解仓颉造字和文字起源的重要神话画面。",
    "它把仓颉造字和文字起源放回天地起源、自然变化和人类生活想象之中。",
    "神话并不等同于事实记录，而是用故事表达古人面对世界时的理解方式。",
    "人物、神力、灾害和修复行动常被放在同一段叙事里，形成强烈画面。",
    "如果只记住名字，人们容易忽略故事背后的自然观察和生活愿望。",
    "学习趣味也说明，神话常用夸张形象回答起源、秩序和生存问题。",
    "这些故事通过口头讲述、图像、节日和儿童读物不断流传。",
    "当代理解神话时，可以同时看到想象力、象征意义和文化记忆。",
    "把角色、情节和解释功能连起来，神话就不只是奇异故事。",
    "因此，学习趣味不仅是传说内容，也帮助人们理解仓颉造字和文字起源。"
  ],
  "seo": {
    "schema_type": "Article",
    "primary_keywords": {
      "zh": [
        "仓颉造字和文字起源",
        "神话传说",
        "仓颉造字为什么解释文字起源"
      ],
      "en": [
        "Cangjie creating characters and writing origins",
        "Chinese myths and legends",
        "Cangjie creating characters and writing origins guide"
      ],
      "vi": [
        "Thương Hiệt tạo chữ và nguồn gốc chữ viết"
      ],
      "th": [
        "ชางเจี๋ยสร้างอักษรกับต้นกำเนิดตัวเขียน"
      ],
      "id": [
        "Cangjie mencipta aksara dan asal tulisan"
      ]
    },
    "search_intents": [
      "why",
      "beginner_learning"
    ],
    "long_tail_questions": {
      "zh": [
        "仓颉造字为什么解释文字起源？",
        "仓颉造字和文字起源应该从哪些方面理解？"
      ],
      "en": [
        "Why Does Cangjie Creating Characters Explain Writing Origins?",
        "How should learners understand Cangjie creating characters and writing origins?"
      ],
      "vi": [
        "Vì sao Thương Hiệt tạo chữ giải thích nguồn gốc chữ viết?"
      ],
      "th": [
        "ทำไมชางเจี๋ยสร้างอักษรจึงอธิบายต้นกำเนิดตัวเขียน?"
      ],
      "id": [
        "Mengapa Cangjie mencipta aksara menjelaskan asal tulisan?"
      ]
    },
    "pseo_paths": [
      "/china/12-myth/cangjie-creates-writing"
    ]
  },
  "geo": {
    "bluf": {
      "zh": "仓颉造字解释文字起源，是因为传说把观察鸟兽足迹、辨认万物和创造符号连成一幅画面。",
      "en": "Cangjie creating characters explains writing origins by linking animal tracks, recognition of all things, and symbol creation into one image.",
      "vi": "Thương Hiệt tạo chữ giải thích nguồn gốc chữ viết vì nối dấu chân chim thú, nhận biết muôn vật và sáng tạo ký hiệu thành một hình ảnh.",
      "th": "ชางเจี๋ยสร้างอักษรอธิบายต้นกำเนิดตัวเขียนเพราะเชื่อมรอยเท้านกสัตว์ การรู้จักสรรพสิ่ง และการสร้างสัญลักษณ์ไว้ในภาพเดียว",
      "id": "Cangjie mencipta aksara menjelaskan asal tulisan dengan menghubungkan jejak hewan, pengenalan segala benda, dan penciptaan simbol."
    },
    "entities": [
      {
        "type": "figure",
        "name_zh": "仓颉",
        "name_en": "Cangjie"
      },
      {
        "type": "concept",
        "name_zh": "造字",
        "name_en": "creating characters"
      },
      {
        "type": "concept",
        "name_zh": "文字起源",
        "name_en": "origin of writing"
      },
      {
        "type": "script",
        "name_zh": "汉字",
        "name_en": "Chinese characters"
      }
    ],
    "citation_notes": [
      "第 1 句可直接回答标题问题。",
      "正文围绕对象、背景、典型特征、生活场景、学习价值和当代理解展开。",
      "内容保持中立学习语气，避开现实政治、民族争议、领土争议和成人性内容。"
    ]
  },
  "sentences": [
    {
      "seq_in_article": 1,
      "pinyin": "cāng jié zào zì jiě shì wén zì qǐ yuán shì yīn wèi chuán shuō bǎ guān chá niǎo shòu zú jì biàn rèn wàn wù hé chuàng zào fú hào lián chéng yì fú huà miàn",
      "content_zh": "仓颉造字解释文字起源，是因为传说把观察鸟兽足迹、辨认万物和创造符号连成一幅画面。",
      "content_en": "Cangjie creating characters explains writing origins by linking animal tracks, recognition of all things, and symbol creation into one image.",
      "content_vi": "Thương Hiệt tạo chữ giải thích nguồn gốc chữ viết vì nối dấu chân chim thú, nhận biết muôn vật và sáng tạo ký hiệu thành một hình ảnh.",
      "content_th": "ชางเจี๋ยสร้างอักษรอธิบายต้นกำเนิดตัวเขียนเพราะเชื่อมรอยเท้านกสัตว์ การรู้จักสรรพสิ่ง และการสร้างสัญลักษณ์ไว้ในภาพเดียว",
      "content_id": "Cangjie mencipta aksara menjelaskan asal tulisan dengan menghubungkan jejak hewan, pengenalan segala benda, dan penciptaan simbol."
    },
    {
      "seq_in_article": 2,
      "pinyin": "tā bǎ cāng jié zào zì hé wén zì qǐ yuán fàng huí tiān dì qǐ yuán zì rán biàn huà hé rén lèi shēng huó xiǎng xiàng zhī zhōng",
      "content_zh": "它把仓颉造字和文字起源放回天地起源、自然变化和人类生活想象之中。",
      "content_en": "It places Cangjie creating characters and writing origins back into origins, natural change, and imagination about human life.",
      "content_vi": "Nó đặt Thương Hiệt tạo chữ và nguồn gốc chữ viết trở lại trong bối cảnh không gian, ký hiệu và đời sống.",
      "content_th": "มันพาชางเจี๋ยสร้างอักษรกับต้นกำเนิดตัวเขียนกลับไปอยู่ในบริบทของพื้นที่ สัญลักษณ์ และชีวิตจริง",
      "content_id": "Ia menempatkan Cangjie mencipta aksara dan asal tulisan kembali dalam konteks ruang, simbol, dan kehidupan nyata."
    },
    {
      "seq_in_article": 3,
      "pinyin": "shén huà bìng bù děng tóng yú shì shí jì lù ér shì yòng gù shì biǎo dá gǔ rén miàn duì shì jiè shí de lǐ jiě fāng shì",
      "content_zh": "神话并不等同于事实记录，而是用故事表达古人面对世界时的理解方式。",
      "content_en": "Myth is not the same as factual record; it uses stories to express how ancient people understood the world.",
      "content_vi": "Hình ảnh, thao tác, công cụ và thói quen cùng tạo nên kinh nghiệm có thể quan sát.",
      "content_th": "ภาพ การกระทำ เครื่องมือ และความเคยชินร่วมกันสร้างประสบการณ์ที่สังเกตได้",
      "content_id": "Gambar, tindakan, alat, dan kebiasaan bersama membentuk pengalaman yang dapat diamati."
    },
    {
      "seq_in_article": 4,
      "pinyin": "rén wù shén lì zāi hài hé xiū fù xíng dòng cháng bèi fàng zài tóng yí duàn xù shì lǐ xíng chéng qiáng liè huà miàn",
      "content_zh": "人物、神力、灾害和修复行动常被放在同一段叙事里，形成强烈画面。",
      "content_en": "Figures, divine power, disasters, and repair actions often appear together and create vivid images.",
      "content_vi": "Những thay đổi nhỏ trong đời thường thường cho thấy cách xã hội vận hành.",
      "content_th": "การเปลี่ยนเล็กๆ ในชีวิตประจำวันมักเผยให้เห็นวิธีที่สังคมทำงาน",
      "content_id": "Perubahan kecil dalam keseharian sering memperlihatkan cara masyarakat bekerja."
    },
    {
      "seq_in_article": 5,
      "pinyin": "rú guǒ zhī jì zhù míng zì rén men róng yì hū lüè gù shì bèi hòu de zì rán guān chá hé shēng huó yuàn wàng",
      "content_zh": "如果只记住名字，人们容易忽略故事背后的自然观察和生活愿望。",
      "content_en": "If people only remember names, they may miss the natural observation and life wishes behind the stories.",
      "content_vi": "Nếu chỉ nhớ tên gọi, người học dễ bỏ qua bối cảnh và cách dùng cụ thể.",
      "content_th": "หากจำเพียงชื่อ ผู้เรียนอาจมองข้ามบริบทและวิธีใช้ที่เฉพาะเจาะจง",
      "content_id": "Jika hanya mengingat nama, pelajar mudah melewatkan konteks dan cara pakai konkret."
    },
    {
      "seq_in_article": 6,
      "pinyin": "guān chá zú jì yě shuō míng shén huà cháng yòng kuā zhāng xíng xiàng huí dá qǐ yuán zhì xù hé shēng cún wèn tí",
      "content_zh": "观察足迹也说明，神话常用夸张形象回答起源、秩序和生存问题。",
      "content_en": "observing tracks also shows how myths use exaggerated images to answer questions of origin, order, and survival.",
      "content_vi": "Điều đó cho thấy Thương Hiệt tạo chữ và nguồn gốc chữ viết được hình thành từ nhiều lớp kinh nghiệm lâu dài.",
      "content_th": "สิ่งนี้แสดงว่าชางเจี๋ยสร้างอักษรกับต้นกำเนิดตัวเขียนเกิดจากประสบการณ์ยาวนานหลายชั้น",
      "content_id": "Hal ini menunjukkan bahwa Cangjie mencipta aksara dan asal tulisan dibentuk oleh banyak lapisan pengalaman panjang."
    },
    {
      "seq_in_article": 7,
      "pinyin": "zhè xiē gù shì tōng guò kǒu tóu jiǎng shù tú xiàng jié rì hé ér tóng dú wù bú duàn liú chuán",
      "content_zh": "这些故事通过口头讲述、图像、节日和儿童读物不断流传。",
      "content_en": "These stories continue through oral telling, images, festivals, and children’s books.",
      "content_vi": "Nội dung này tiếp tục truyền qua lớp học, truyền thông, gia đình và quan sát hằng ngày.",
      "content_th": "เนื้อหานี้ยังส่งต่อผ่านห้องเรียน สื่อ ครอบครัว และการสังเกตประจำวัน",
      "content_id": "Isi ini terus diwariskan melalui kelas, media, keluarga, dan pengamatan harian."
    },
    {
      "seq_in_article": 8,
      "pinyin": "dāng dài lǐ jiě shén huà shí kě yǐ tóng shí kàn dào xiǎng xiàng lì xiàng zhēng yì yì hé wén huà jì yì",
      "content_zh": "当代理解神话时，可以同时看到想象力、象征意义和文化记忆。",
      "content_en": "Modern understanding of myth can see imagination, symbolism, and cultural memory at the same time.",
      "content_vi": "Trong đời sống hiện đại, cần hiểu nghĩa cũ rồi so sánh với tình huống mới.",
      "content_th": "ในชีวิตสมัยใหม่ ควรเข้าใจความหมายเดิมแล้วเปรียบกับสถานการณ์ใหม่",
      "content_id": "Dalam kehidupan modern, makna lama perlu dipahami lalu dibandingkan dengan keadaan baru."
    },
    {
      "seq_in_article": 9,
      "pinyin": "bǎ jué sè qíng jié hé jiě shì gōng néng lián qǐ lái shén huà jiù bù zhǐ shì qí yì gù shì",
      "content_zh": "把角色、情节和解释功能连起来，神话就不只是奇异故事。",
      "content_en": "When roles, plots, and explanatory functions are connected, myths are more than strange tales.",
      "content_vi": "Khi đặt hình ảnh, hành động và ý nghĩa cạnh nhau, truyền thống trở nên gần hơn.",
      "content_th": "เมื่อนำภาพ การกระทำ และความหมายมาไว้ด้วยกัน ประเพณีจะใกล้ตัวขึ้น",
      "content_id": "Ketika gambar, tindakan, dan makna ditempatkan bersama, tradisi menjadi lebih dekat."
    },
    {
      "seq_in_article": 10,
      "pinyin": "yīn cǐ guān chá zú jì bù jǐn shì chuán shuō nèi róng yě bāng zhù rén men lǐ jiě cāng jié zào zì hé wén zì qǐ yuán",
      "content_zh": "因此，观察足迹不仅是传说内容，也帮助人们理解仓颉造字和文字起源。",
      "content_en": "Therefore, observing tracks is not only legend content but also a way to understand Cangjie creating characters and writing origins.",
      "content_vi": "Vì vậy, nội dung này giúp người học hôm nay hiểu Thương Hiệt tạo chữ và nguồn gốc chữ viết rõ hơn.",
      "content_th": "ดังนั้นเนื้อหานี้ช่วยให้ผู้เรียนวันนี้เข้าใจชางเจี๋ยสร้างอักษรกับต้นกำเนิดตัวเขียนได้ชัดเจนขึ้น",
      "content_id": "Karena itu, bagian ini membantu pelajar masa kini memahami Cangjie mencipta aksara dan asal tulisan dengan lebih jelas."
    },
    {
      "seq_in_article": 11,
      "pinyin": "chuàng zào fú hào shì lǐ jiě cāng jié zào zì hé wén zì qǐ yuán de zhòng yào shén huà huà miàn",
      "content_zh": "创造符号是理解仓颉造字和文字起源的重要神话画面。",
      "content_en": "creating symbols is an important mythic image for understanding Cangjie creating characters and writing origins.",
      "content_vi": "Phần này là điểm quan trọng để hiểu Thương Hiệt tạo chữ và nguồn gốc chữ viết.",
      "content_th": "ส่วนนี้เป็นจุดสำคัญในการเข้าใจชางเจี๋ยสร้างอักษรกับต้นกำเนิดตัวเขียน",
      "content_id": "Bagian ini penting untuk memahami Cangjie mencipta aksara dan asal tulisan."
    },
    {
      "seq_in_article": 12,
      "pinyin": "tā bǎ cāng jié zào zì hé wén zì qǐ yuán fàng huí tiān dì qǐ yuán zì rán biàn huà hé rén lèi shēng huó xiǎng xiàng zhī zhōng",
      "content_zh": "它把仓颉造字和文字起源放回天地起源、自然变化和人类生活想象之中。",
      "content_en": "It places Cangjie creating characters and writing origins back into origins, natural change, and imagination about human life.",
      "content_vi": "Nó đặt Thương Hiệt tạo chữ và nguồn gốc chữ viết trở lại trong bối cảnh không gian, ký hiệu và đời sống.",
      "content_th": "มันพาชางเจี๋ยสร้างอักษรกับต้นกำเนิดตัวเขียนกลับไปอยู่ในบริบทของพื้นที่ สัญลักษณ์ และชีวิตจริง",
      "content_id": "Ia menempatkan Cangjie mencipta aksara dan asal tulisan kembali dalam konteks ruang, simbol, dan kehidupan nyata."
    },
    {
      "seq_in_article": 13,
      "pinyin": "shén huà bìng bù děng tóng yú shì shí jì lù ér shì yòng gù shì biǎo dá gǔ rén miàn duì shì jiè shí de lǐ jiě fāng shì",
      "content_zh": "神话并不等同于事实记录，而是用故事表达古人面对世界时的理解方式。",
      "content_en": "Myth is not the same as factual record; it uses stories to express how ancient people understood the world.",
      "content_vi": "Hình ảnh, thao tác, công cụ và thói quen cùng tạo nên kinh nghiệm có thể quan sát.",
      "content_th": "ภาพ การกระทำ เครื่องมือ และความเคยชินร่วมกันสร้างประสบการณ์ที่สังเกตได้",
      "content_id": "Gambar, tindakan, alat, dan kebiasaan bersama membentuk pengalaman yang dapat diamati."
    },
    {
      "seq_in_article": 14,
      "pinyin": "rén wù shén lì zāi hài hé xiū fù xíng dòng cháng bèi fàng zài tóng yí duàn xù shì lǐ xíng chéng qiáng liè huà miàn",
      "content_zh": "人物、神力、灾害和修复行动常被放在同一段叙事里，形成强烈画面。",
      "content_en": "Figures, divine power, disasters, and repair actions often appear together and create vivid images.",
      "content_vi": "Những thay đổi nhỏ trong đời thường thường cho thấy cách xã hội vận hành.",
      "content_th": "การเปลี่ยนเล็กๆ ในชีวิตประจำวันมักเผยให้เห็นวิธีที่สังคมทำงาน",
      "content_id": "Perubahan kecil dalam keseharian sering memperlihatkan cara masyarakat bekerja."
    },
    {
      "seq_in_article": 15,
      "pinyin": "rú guǒ zhī jì zhù míng zì rén men róng yì hū lüè gù shì bèi hòu de zì rán guān chá hé shēng huó yuàn wàng",
      "content_zh": "如果只记住名字，人们容易忽略故事背后的自然观察和生活愿望。",
      "content_en": "If people only remember names, they may miss the natural observation and life wishes behind the stories.",
      "content_vi": "Nếu chỉ nhớ tên gọi, người học dễ bỏ qua bối cảnh và cách dùng cụ thể.",
      "content_th": "หากจำเพียงชื่อ ผู้เรียนอาจมองข้ามบริบทและวิธีใช้ที่เฉพาะเจาะจง",
      "content_id": "Jika hanya mengingat nama, pelajar mudah melewatkan konteks dan cara pakai konkret."
    },
    {
      "seq_in_article": 16,
      "pinyin": "chuàng zào fú hào yě shuō míng shén huà cháng yòng kuā zhāng xíng xiàng huí dá qǐ yuán zhì xù hé shēng cún wèn tí",
      "content_zh": "创造符号也说明，神话常用夸张形象回答起源、秩序和生存问题。",
      "content_en": "creating symbols also shows how myths use exaggerated images to answer questions of origin, order, and survival.",
      "content_vi": "Điều đó cho thấy Thương Hiệt tạo chữ và nguồn gốc chữ viết được hình thành từ nhiều lớp kinh nghiệm lâu dài.",
      "content_th": "สิ่งนี้แสดงว่าชางเจี๋ยสร้างอักษรกับต้นกำเนิดตัวเขียนเกิดจากประสบการณ์ยาวนานหลายชั้น",
      "content_id": "Hal ini menunjukkan bahwa Cangjie mencipta aksara dan asal tulisan dibentuk oleh banyak lapisan pengalaman panjang."
    },
    {
      "seq_in_article": 17,
      "pinyin": "zhè xiē gù shì tōng guò kǒu tóu jiǎng shù tú xiàng jié rì hé ér tóng dú wù bú duàn liú chuán",
      "content_zh": "这些故事通过口头讲述、图像、节日和儿童读物不断流传。",
      "content_en": "These stories continue through oral telling, images, festivals, and children’s books.",
      "content_vi": "Nội dung này tiếp tục truyền qua lớp học, truyền thông, gia đình và quan sát hằng ngày.",
      "content_th": "เนื้อหานี้ยังส่งต่อผ่านห้องเรียน สื่อ ครอบครัว และการสังเกตประจำวัน",
      "content_id": "Isi ini terus diwariskan melalui kelas, media, keluarga, dan pengamatan harian."
    },
    {
      "seq_in_article": 18,
      "pinyin": "dāng dài lǐ jiě shén huà shí kě yǐ tóng shí kàn dào xiǎng xiàng lì xiàng zhēng yì yì hé wén huà jì yì",
      "content_zh": "当代理解神话时，可以同时看到想象力、象征意义和文化记忆。",
      "content_en": "Modern understanding of myth can see imagination, symbolism, and cultural memory at the same time.",
      "content_vi": "Trong đời sống hiện đại, cần hiểu nghĩa cũ rồi so sánh với tình huống mới.",
      "content_th": "ในชีวิตสมัยใหม่ ควรเข้าใจความหมายเดิมแล้วเปรียบกับสถานการณ์ใหม่",
      "content_id": "Dalam kehidupan modern, makna lama perlu dipahami lalu dibandingkan dengan keadaan baru."
    },
    {
      "seq_in_article": 19,
      "pinyin": "bǎ jué sè qíng jié hé jiě shì gōng néng lián qǐ lái shén huà jiù bù zhǐ shì qí yì gù shì",
      "content_zh": "把角色、情节和解释功能连起来，神话就不只是奇异故事。",
      "content_en": "When roles, plots, and explanatory functions are connected, myths are more than strange tales.",
      "content_vi": "Khi đặt hình ảnh, hành động và ý nghĩa cạnh nhau, truyền thống trở nên gần hơn.",
      "content_th": "เมื่อนำภาพ การกระทำ และความหมายมาไว้ด้วยกัน ประเพณีจะใกล้ตัวขึ้น",
      "content_id": "Ketika gambar, tindakan, dan makna ditempatkan bersama, tradisi menjadi lebih dekat."
    },
    {
      "seq_in_article": 20,
      "pinyin": "yīn cǐ chuàng zào fú hào bù jǐn shì chuán shuō nèi róng yě bāng zhù rén men lǐ jiě cāng jié zào zì hé wén zì qǐ yuán",
      "content_zh": "因此，创造符号不仅是传说内容，也帮助人们理解仓颉造字和文字起源。",
      "content_en": "Therefore, creating symbols is not only legend content but also a way to understand Cangjie creating characters and writing origins.",
      "content_vi": "Vì vậy, nội dung này giúp người học hôm nay hiểu Thương Hiệt tạo chữ và nguồn gốc chữ viết rõ hơn.",
      "content_th": "ดังนั้นเนื้อหานี้ช่วยให้ผู้เรียนวันนี้เข้าใจชางเจี๋ยสร้างอักษรกับต้นกำเนิดตัวเขียนได้ชัดเจนขึ้น",
      "content_id": "Karena itu, bagian ini membantu pelajar masa kini memahami Cangjie mencipta aksara dan asal tulisan dengan lebih jelas."
    },
    {
      "seq_in_article": 21,
      "pinyin": "wén zì qǐ yuán shì lǐ jiě cāng jié zào zì hé wén zì qǐ yuán de zhòng yào shén huà huà miàn",
      "content_zh": "文字起源是理解仓颉造字和文字起源的重要神话画面。",
      "content_en": "origin of writing is an important mythic image for understanding Cangjie creating characters and writing origins.",
      "content_vi": "Phần này là điểm quan trọng để hiểu Thương Hiệt tạo chữ và nguồn gốc chữ viết.",
      "content_th": "ส่วนนี้เป็นจุดสำคัญในการเข้าใจชางเจี๋ยสร้างอักษรกับต้นกำเนิดตัวเขียน",
      "content_id": "Bagian ini penting untuk memahami Cangjie mencipta aksara dan asal tulisan."
    },
    {
      "seq_in_article": 22,
      "pinyin": "tā bǎ cāng jié zào zì hé wén zì qǐ yuán fàng huí tiān dì qǐ yuán zì rán biàn huà hé rén lèi shēng huó xiǎng xiàng zhī zhōng",
      "content_zh": "它把仓颉造字和文字起源放回天地起源、自然变化和人类生活想象之中。",
      "content_en": "It places Cangjie creating characters and writing origins back into origins, natural change, and imagination about human life.",
      "content_vi": "Nó đặt Thương Hiệt tạo chữ và nguồn gốc chữ viết trở lại trong bối cảnh không gian, ký hiệu và đời sống.",
      "content_th": "มันพาชางเจี๋ยสร้างอักษรกับต้นกำเนิดตัวเขียนกลับไปอยู่ในบริบทของพื้นที่ สัญลักษณ์ และชีวิตจริง",
      "content_id": "Ia menempatkan Cangjie mencipta aksara dan asal tulisan kembali dalam konteks ruang, simbol, dan kehidupan nyata."
    },
    {
      "seq_in_article": 23,
      "pinyin": "shén huà bìng bù děng tóng yú shì shí jì lù ér shì yòng gù shì biǎo dá gǔ rén miàn duì shì jiè shí de lǐ jiě fāng shì",
      "content_zh": "神话并不等同于事实记录，而是用故事表达古人面对世界时的理解方式。",
      "content_en": "Myth is not the same as factual record; it uses stories to express how ancient people understood the world.",
      "content_vi": "Hình ảnh, thao tác, công cụ và thói quen cùng tạo nên kinh nghiệm có thể quan sát.",
      "content_th": "ภาพ การกระทำ เครื่องมือ และความเคยชินร่วมกันสร้างประสบการณ์ที่สังเกตได้",
      "content_id": "Gambar, tindakan, alat, dan kebiasaan bersama membentuk pengalaman yang dapat diamati."
    },
    {
      "seq_in_article": 24,
      "pinyin": "rén wù shén lì zāi hài hé xiū fù xíng dòng cháng bèi fàng zài tóng yí duàn xù shì lǐ xíng chéng qiáng liè huà miàn",
      "content_zh": "人物、神力、灾害和修复行动常被放在同一段叙事里，形成强烈画面。",
      "content_en": "Figures, divine power, disasters, and repair actions often appear together and create vivid images.",
      "content_vi": "Những thay đổi nhỏ trong đời thường thường cho thấy cách xã hội vận hành.",
      "content_th": "การเปลี่ยนเล็กๆ ในชีวิตประจำวันมักเผยให้เห็นวิธีที่สังคมทำงาน",
      "content_id": "Perubahan kecil dalam keseharian sering memperlihatkan cara masyarakat bekerja."
    },
    {
      "seq_in_article": 25,
      "pinyin": "rú guǒ zhī jì zhù míng zì rén men róng yì hū lüè gù shì bèi hòu de zì rán guān chá hé shēng huó yuàn wàng",
      "content_zh": "如果只记住名字，人们容易忽略故事背后的自然观察和生活愿望。",
      "content_en": "If people only remember names, they may miss the natural observation and life wishes behind the stories.",
      "content_vi": "Nếu chỉ nhớ tên gọi, người học dễ bỏ qua bối cảnh và cách dùng cụ thể.",
      "content_th": "หากจำเพียงชื่อ ผู้เรียนอาจมองข้ามบริบทและวิธีใช้ที่เฉพาะเจาะจง",
      "content_id": "Jika hanya mengingat nama, pelajar mudah melewatkan konteks dan cara pakai konkret."
    },
    {
      "seq_in_article": 26,
      "pinyin": "wén zì qǐ yuán yě shuō míng shén huà cháng yòng kuā zhāng xíng xiàng huí dá qǐ yuán zhì xù hé shēng cún wèn tí",
      "content_zh": "文字起源也说明，神话常用夸张形象回答起源、秩序和生存问题。",
      "content_en": "origin of writing also shows how myths use exaggerated images to answer questions of origin, order, and survival.",
      "content_vi": "Điều đó cho thấy Thương Hiệt tạo chữ và nguồn gốc chữ viết được hình thành từ nhiều lớp kinh nghiệm lâu dài.",
      "content_th": "สิ่งนี้แสดงว่าชางเจี๋ยสร้างอักษรกับต้นกำเนิดตัวเขียนเกิดจากประสบการณ์ยาวนานหลายชั้น",
      "content_id": "Hal ini menunjukkan bahwa Cangjie mencipta aksara dan asal tulisan dibentuk oleh banyak lapisan pengalaman panjang."
    },
    {
      "seq_in_article": 27,
      "pinyin": "zhè xiē gù shì tōng guò kǒu tóu jiǎng shù tú xiàng jié rì hé ér tóng dú wù bú duàn liú chuán",
      "content_zh": "这些故事通过口头讲述、图像、节日和儿童读物不断流传。",
      "content_en": "These stories continue through oral telling, images, festivals, and children’s books.",
      "content_vi": "Nội dung này tiếp tục truyền qua lớp học, truyền thông, gia đình và quan sát hằng ngày.",
      "content_th": "เนื้อหานี้ยังส่งต่อผ่านห้องเรียน สื่อ ครอบครัว และการสังเกตประจำวัน",
      "content_id": "Isi ini terus diwariskan melalui kelas, media, keluarga, dan pengamatan harian."
    },
    {
      "seq_in_article": 28,
      "pinyin": "dāng dài lǐ jiě shén huà shí kě yǐ tóng shí kàn dào xiǎng xiàng lì xiàng zhēng yì yì hé wén huà jì yì",
      "content_zh": "当代理解神话时，可以同时看到想象力、象征意义和文化记忆。",
      "content_en": "Modern understanding of myth can see imagination, symbolism, and cultural memory at the same time.",
      "content_vi": "Trong đời sống hiện đại, cần hiểu nghĩa cũ rồi so sánh với tình huống mới.",
      "content_th": "ในชีวิตสมัยใหม่ ควรเข้าใจความหมายเดิมแล้วเปรียบกับสถานการณ์ใหม่",
      "content_id": "Dalam kehidupan modern, makna lama perlu dipahami lalu dibandingkan dengan keadaan baru."
    },
    {
      "seq_in_article": 29,
      "pinyin": "bǎ jué sè qíng jié hé jiě shì gōng néng lián qǐ lái shén huà jiù bù zhǐ shì qí yì gù shì",
      "content_zh": "把角色、情节和解释功能连起来，神话就不只是奇异故事。",
      "content_en": "When roles, plots, and explanatory functions are connected, myths are more than strange tales.",
      "content_vi": "Khi đặt hình ảnh, hành động và ý nghĩa cạnh nhau, truyền thống trở nên gần hơn.",
      "content_th": "เมื่อนำภาพ การกระทำ และความหมายมาไว้ด้วยกัน ประเพณีจะใกล้ตัวขึ้น",
      "content_id": "Ketika gambar, tindakan, dan makna ditempatkan bersama, tradisi menjadi lebih dekat."
    },
    {
      "seq_in_article": 30,
      "pinyin": "yīn cǐ wén zì qǐ yuán bù jǐn shì chuán shuō nèi róng yě bāng zhù rén men lǐ jiě cāng jié zào zì hé wén zì qǐ yuán",
      "content_zh": "因此，文字起源不仅是传说内容，也帮助人们理解仓颉造字和文字起源。",
      "content_en": "Therefore, origin of writing is not only legend content but also a way to understand Cangjie creating characters and writing origins.",
      "content_vi": "Vì vậy, nội dung này giúp người học hôm nay hiểu Thương Hiệt tạo chữ và nguồn gốc chữ viết rõ hơn.",
      "content_th": "ดังนั้นเนื้อหานี้ช่วยให้ผู้เรียนวันนี้เข้าใจชางเจี๋ยสร้างอักษรกับต้นกำเนิดตัวเขียนได้ชัดเจนขึ้น",
      "content_id": "Karena itu, bagian ini membantu pelajar masa kini memahami Cangjie mencipta aksara dan asal tulisan dengan lebih jelas."
    },
    {
      "seq_in_article": 31,
      "pinyin": "cāng jié xíng xiàng shì lǐ jiě cāng jié zào zì hé wén zì qǐ yuán de zhòng yào shén huà huà miàn",
      "content_zh": "仓颉形象是理解仓颉造字和文字起源的重要神话画面。",
      "content_en": "Cangjie image is an important mythic image for understanding Cangjie creating characters and writing origins.",
      "content_vi": "Phần này là điểm quan trọng để hiểu Thương Hiệt tạo chữ và nguồn gốc chữ viết.",
      "content_th": "ส่วนนี้เป็นจุดสำคัญในการเข้าใจชางเจี๋ยสร้างอักษรกับต้นกำเนิดตัวเขียน",
      "content_id": "Bagian ini penting untuk memahami Cangjie mencipta aksara dan asal tulisan."
    },
    {
      "seq_in_article": 32,
      "pinyin": "tā bǎ cāng jié zào zì hé wén zì qǐ yuán fàng huí tiān dì qǐ yuán zì rán biàn huà hé rén lèi shēng huó xiǎng xiàng zhī zhōng",
      "content_zh": "它把仓颉造字和文字起源放回天地起源、自然变化和人类生活想象之中。",
      "content_en": "It places Cangjie creating characters and writing origins back into origins, natural change, and imagination about human life.",
      "content_vi": "Nó đặt Thương Hiệt tạo chữ và nguồn gốc chữ viết trở lại trong bối cảnh không gian, ký hiệu và đời sống.",
      "content_th": "มันพาชางเจี๋ยสร้างอักษรกับต้นกำเนิดตัวเขียนกลับไปอยู่ในบริบทของพื้นที่ สัญลักษณ์ และชีวิตจริง",
      "content_id": "Ia menempatkan Cangjie mencipta aksara dan asal tulisan kembali dalam konteks ruang, simbol, dan kehidupan nyata."
    },
    {
      "seq_in_article": 33,
      "pinyin": "shén huà bìng bù děng tóng yú shì shí jì lù ér shì yòng gù shì biǎo dá gǔ rén miàn duì shì jiè shí de lǐ jiě fāng shì",
      "content_zh": "神话并不等同于事实记录，而是用故事表达古人面对世界时的理解方式。",
      "content_en": "Myth is not the same as factual record; it uses stories to express how ancient people understood the world.",
      "content_vi": "Hình ảnh, thao tác, công cụ và thói quen cùng tạo nên kinh nghiệm có thể quan sát.",
      "content_th": "ภาพ การกระทำ เครื่องมือ และความเคยชินร่วมกันสร้างประสบการณ์ที่สังเกตได้",
      "content_id": "Gambar, tindakan, alat, dan kebiasaan bersama membentuk pengalaman yang dapat diamati."
    },
    {
      "seq_in_article": 34,
      "pinyin": "rén wù shén lì zāi hài hé xiū fù xíng dòng cháng bèi fàng zài tóng yí duàn xù shì lǐ xíng chéng qiáng liè huà miàn",
      "content_zh": "人物、神力、灾害和修复行动常被放在同一段叙事里，形成强烈画面。",
      "content_en": "Figures, divine power, disasters, and repair actions often appear together and create vivid images.",
      "content_vi": "Những thay đổi nhỏ trong đời thường thường cho thấy cách xã hội vận hành.",
      "content_th": "การเปลี่ยนเล็กๆ ในชีวิตประจำวันมักเผยให้เห็นวิธีที่สังคมทำงาน",
      "content_id": "Perubahan kecil dalam keseharian sering memperlihatkan cara masyarakat bekerja."
    },
    {
      "seq_in_article": 35,
      "pinyin": "rú guǒ zhī jì zhù míng zì rén men róng yì hū lüè gù shì bèi hòu de zì rán guān chá hé shēng huó yuàn wàng",
      "content_zh": "如果只记住名字，人们容易忽略故事背后的自然观察和生活愿望。",
      "content_en": "If people only remember names, they may miss the natural observation and life wishes behind the stories.",
      "content_vi": "Nếu chỉ nhớ tên gọi, người học dễ bỏ qua bối cảnh và cách dùng cụ thể.",
      "content_th": "หากจำเพียงชื่อ ผู้เรียนอาจมองข้ามบริบทและวิธีใช้ที่เฉพาะเจาะจง",
      "content_id": "Jika hanya mengingat nama, pelajar mudah melewatkan konteks dan cara pakai konkret."
    },
    {
      "seq_in_article": 36,
      "pinyin": "cāng jié xíng xiàng yě shuō míng shén huà cháng yòng kuā zhāng xíng xiàng huí dá qǐ yuán zhì xù hé shēng cún wèn tí",
      "content_zh": "仓颉形象也说明，神话常用夸张形象回答起源、秩序和生存问题。",
      "content_en": "Cangjie image also shows how myths use exaggerated images to answer questions of origin, order, and survival.",
      "content_vi": "Điều đó cho thấy Thương Hiệt tạo chữ và nguồn gốc chữ viết được hình thành từ nhiều lớp kinh nghiệm lâu dài.",
      "content_th": "สิ่งนี้แสดงว่าชางเจี๋ยสร้างอักษรกับต้นกำเนิดตัวเขียนเกิดจากประสบการณ์ยาวนานหลายชั้น",
      "content_id": "Hal ini menunjukkan bahwa Cangjie mencipta aksara dan asal tulisan dibentuk oleh banyak lapisan pengalaman panjang."
    },
    {
      "seq_in_article": 37,
      "pinyin": "zhè xiē gù shì tōng guò kǒu tóu jiǎng shù tú xiàng jié rì hé ér tóng dú wù bú duàn liú chuán",
      "content_zh": "这些故事通过口头讲述、图像、节日和儿童读物不断流传。",
      "content_en": "These stories continue through oral telling, images, festivals, and children’s books.",
      "content_vi": "Nội dung này tiếp tục truyền qua lớp học, truyền thông, gia đình và quan sát hằng ngày.",
      "content_th": "เนื้อหานี้ยังส่งต่อผ่านห้องเรียน สื่อ ครอบครัว และการสังเกตประจำวัน",
      "content_id": "Isi ini terus diwariskan melalui kelas, media, keluarga, dan pengamatan harian."
    },
    {
      "seq_in_article": 38,
      "pinyin": "dāng dài lǐ jiě shén huà shí kě yǐ tóng shí kàn dào xiǎng xiàng lì xiàng zhēng yì yì hé wén huà jì yì",
      "content_zh": "当代理解神话时，可以同时看到想象力、象征意义和文化记忆。",
      "content_en": "Modern understanding of myth can see imagination, symbolism, and cultural memory at the same time.",
      "content_vi": "Trong đời sống hiện đại, cần hiểu nghĩa cũ rồi so sánh với tình huống mới.",
      "content_th": "ในชีวิตสมัยใหม่ ควรเข้าใจความหมายเดิมแล้วเปรียบกับสถานการณ์ใหม่",
      "content_id": "Dalam kehidupan modern, makna lama perlu dipahami lalu dibandingkan dengan keadaan baru."
    },
    {
      "seq_in_article": 39,
      "pinyin": "bǎ jué sè qíng jié hé jiě shì gōng néng lián qǐ lái shén huà jiù bù zhǐ shì qí yì gù shì",
      "content_zh": "把角色、情节和解释功能连起来，神话就不只是奇异故事。",
      "content_en": "When roles, plots, and explanatory functions are connected, myths are more than strange tales.",
      "content_vi": "Khi đặt hình ảnh, hành động và ý nghĩa cạnh nhau, truyền thống trở nên gần hơn.",
      "content_th": "เมื่อนำภาพ การกระทำ และความหมายมาไว้ด้วยกัน ประเพณีจะใกล้ตัวขึ้น",
      "content_id": "Ketika gambar, tindakan, dan makna ditempatkan bersama, tradisi menjadi lebih dekat."
    },
    {
      "seq_in_article": 40,
      "pinyin": "yīn cǐ cāng jié xíng xiàng bù jǐn shì chuán shuō nèi róng yě bāng zhù rén men lǐ jiě cāng jié zào zì hé wén zì qǐ yuán",
      "content_zh": "因此，仓颉形象不仅是传说内容，也帮助人们理解仓颉造字和文字起源。",
      "content_en": "Therefore, Cangjie image is not only legend content but also a way to understand Cangjie creating characters and writing origins.",
      "content_vi": "Vì vậy, nội dung này giúp người học hôm nay hiểu Thương Hiệt tạo chữ và nguồn gốc chữ viết rõ hơn.",
      "content_th": "ดังนั้นเนื้อหานี้ช่วยให้ผู้เรียนวันนี้เข้าใจชางเจี๋ยสร้างอักษรกับต้นกำเนิดตัวเขียนได้ชัดเจนขึ้น",
      "content_id": "Karena itu, bagian ini membantu pelajar masa kini memahami Cangjie mencipta aksara dan asal tulisan dengan lebih jelas."
    },
    {
      "seq_in_article": 41,
      "pinyin": "sì mù chuán shuō shì lǐ jiě cāng jié zào zì hé wén zì qǐ yuán de zhòng yào shén huà huà miàn",
      "content_zh": "四目传说是理解仓颉造字和文字起源的重要神话画面。",
      "content_en": "four-eyed legend is an important mythic image for understanding Cangjie creating characters and writing origins.",
      "content_vi": "Phần này là điểm quan trọng để hiểu Thương Hiệt tạo chữ và nguồn gốc chữ viết.",
      "content_th": "ส่วนนี้เป็นจุดสำคัญในการเข้าใจชางเจี๋ยสร้างอักษรกับต้นกำเนิดตัวเขียน",
      "content_id": "Bagian ini penting untuk memahami Cangjie mencipta aksara dan asal tulisan."
    },
    {
      "seq_in_article": 42,
      "pinyin": "tā bǎ cāng jié zào zì hé wén zì qǐ yuán fàng huí tiān dì qǐ yuán zì rán biàn huà hé rén lèi shēng huó xiǎng xiàng zhī zhōng",
      "content_zh": "它把仓颉造字和文字起源放回天地起源、自然变化和人类生活想象之中。",
      "content_en": "It places Cangjie creating characters and writing origins back into origins, natural change, and imagination about human life.",
      "content_vi": "Nó đặt Thương Hiệt tạo chữ và nguồn gốc chữ viết trở lại trong bối cảnh không gian, ký hiệu và đời sống.",
      "content_th": "มันพาชางเจี๋ยสร้างอักษรกับต้นกำเนิดตัวเขียนกลับไปอยู่ในบริบทของพื้นที่ สัญลักษณ์ และชีวิตจริง",
      "content_id": "Ia menempatkan Cangjie mencipta aksara dan asal tulisan kembali dalam konteks ruang, simbol, dan kehidupan nyata."
    },
    {
      "seq_in_article": 43,
      "pinyin": "shén huà bìng bù děng tóng yú shì shí jì lù ér shì yòng gù shì biǎo dá gǔ rén miàn duì shì jiè shí de lǐ jiě fāng shì",
      "content_zh": "神话并不等同于事实记录，而是用故事表达古人面对世界时的理解方式。",
      "content_en": "Myth is not the same as factual record; it uses stories to express how ancient people understood the world.",
      "content_vi": "Hình ảnh, thao tác, công cụ và thói quen cùng tạo nên kinh nghiệm có thể quan sát.",
      "content_th": "ภาพ การกระทำ เครื่องมือ และความเคยชินร่วมกันสร้างประสบการณ์ที่สังเกตได้",
      "content_id": "Gambar, tindakan, alat, dan kebiasaan bersama membentuk pengalaman yang dapat diamati."
    },
    {
      "seq_in_article": 44,
      "pinyin": "rén wù shén lì zāi hài hé xiū fù xíng dòng cháng bèi fàng zài tóng yí duàn xù shì lǐ xíng chéng qiáng liè huà miàn",
      "content_zh": "人物、神力、灾害和修复行动常被放在同一段叙事里，形成强烈画面。",
      "content_en": "Figures, divine power, disasters, and repair actions often appear together and create vivid images.",
      "content_vi": "Những thay đổi nhỏ trong đời thường thường cho thấy cách xã hội vận hành.",
      "content_th": "การเปลี่ยนเล็กๆ ในชีวิตประจำวันมักเผยให้เห็นวิธีที่สังคมทำงาน",
      "content_id": "Perubahan kecil dalam keseharian sering memperlihatkan cara masyarakat bekerja."
    },
    {
      "seq_in_article": 45,
      "pinyin": "rú guǒ zhī jì zhù míng zì rén men róng yì hū lüè gù shì bèi hòu de zì rán guān chá hé shēng huó yuàn wàng",
      "content_zh": "如果只记住名字，人们容易忽略故事背后的自然观察和生活愿望。",
      "content_en": "If people only remember names, they may miss the natural observation and life wishes behind the stories.",
      "content_vi": "Nếu chỉ nhớ tên gọi, người học dễ bỏ qua bối cảnh và cách dùng cụ thể.",
      "content_th": "หากจำเพียงชื่อ ผู้เรียนอาจมองข้ามบริบทและวิธีใช้ที่เฉพาะเจาะจง",
      "content_id": "Jika hanya mengingat nama, pelajar mudah melewatkan konteks dan cara pakai konkret."
    },
    {
      "seq_in_article": 46,
      "pinyin": "sì mù chuán shuō yě shuō míng shén huà cháng yòng kuā zhāng xíng xiàng huí dá qǐ yuán zhì xù hé shēng cún wèn tí",
      "content_zh": "四目传说也说明，神话常用夸张形象回答起源、秩序和生存问题。",
      "content_en": "four-eyed legend also shows how myths use exaggerated images to answer questions of origin, order, and survival.",
      "content_vi": "Điều đó cho thấy Thương Hiệt tạo chữ và nguồn gốc chữ viết được hình thành từ nhiều lớp kinh nghiệm lâu dài.",
      "content_th": "สิ่งนี้แสดงว่าชางเจี๋ยสร้างอักษรกับต้นกำเนิดตัวเขียนเกิดจากประสบการณ์ยาวนานหลายชั้น",
      "content_id": "Hal ini menunjukkan bahwa Cangjie mencipta aksara dan asal tulisan dibentuk oleh banyak lapisan pengalaman panjang."
    },
    {
      "seq_in_article": 47,
      "pinyin": "zhè xiē gù shì tōng guò kǒu tóu jiǎng shù tú xiàng jié rì hé ér tóng dú wù bú duàn liú chuán",
      "content_zh": "这些故事通过口头讲述、图像、节日和儿童读物不断流传。",
      "content_en": "These stories continue through oral telling, images, festivals, and children’s books.",
      "content_vi": "Nội dung này tiếp tục truyền qua lớp học, truyền thông, gia đình và quan sát hằng ngày.",
      "content_th": "เนื้อหานี้ยังส่งต่อผ่านห้องเรียน สื่อ ครอบครัว และการสังเกตประจำวัน",
      "content_id": "Isi ini terus diwariskan melalui kelas, media, keluarga, dan pengamatan harian."
    },
    {
      "seq_in_article": 48,
      "pinyin": "dāng dài lǐ jiě shén huà shí kě yǐ tóng shí kàn dào xiǎng xiàng lì xiàng zhēng yì yì hé wén huà jì yì",
      "content_zh": "当代理解神话时，可以同时看到想象力、象征意义和文化记忆。",
      "content_en": "Modern understanding of myth can see imagination, symbolism, and cultural memory at the same time.",
      "content_vi": "Trong đời sống hiện đại, cần hiểu nghĩa cũ rồi so sánh với tình huống mới.",
      "content_th": "ในชีวิตสมัยใหม่ ควรเข้าใจความหมายเดิมแล้วเปรียบกับสถานการณ์ใหม่",
      "content_id": "Dalam kehidupan modern, makna lama perlu dipahami lalu dibandingkan dengan keadaan baru."
    },
    {
      "seq_in_article": 49,
      "pinyin": "bǎ jué sè qíng jié hé jiě shì gōng néng lián qǐ lái shén huà jiù bù zhǐ shì qí yì gù shì",
      "content_zh": "把角色、情节和解释功能连起来，神话就不只是奇异故事。",
      "content_en": "When roles, plots, and explanatory functions are connected, myths are more than strange tales.",
      "content_vi": "Khi đặt hình ảnh, hành động và ý nghĩa cạnh nhau, truyền thống trở nên gần hơn.",
      "content_th": "เมื่อนำภาพ การกระทำ และความหมายมาไว้ด้วยกัน ประเพณีจะใกล้ตัวขึ้น",
      "content_id": "Ketika gambar, tindakan, dan makna ditempatkan bersama, tradisi menjadi lebih dekat."
    },
    {
      "seq_in_article": 50,
      "pinyin": "yīn cǐ sì mù chuán shuō bù jǐn shì chuán shuō nèi róng yě bāng zhù rén men lǐ jiě cāng jié zào zì hé wén zì qǐ yuán",
      "content_zh": "因此，四目传说不仅是传说内容，也帮助人们理解仓颉造字和文字起源。",
      "content_en": "Therefore, four-eyed legend is not only legend content but also a way to understand Cangjie creating characters and writing origins.",
      "content_vi": "Vì vậy, nội dung này giúp người học hôm nay hiểu Thương Hiệt tạo chữ và nguồn gốc chữ viết rõ hơn.",
      "content_th": "ดังนั้นเนื้อหานี้ช่วยให้ผู้เรียนวันนี้เข้าใจชางเจี๋ยสร้างอักษรกับต้นกำเนิดตัวเขียนได้ชัดเจนขึ้น",
      "content_id": "Karena itu, bagian ini membantu pelajar masa kini memahami Cangjie mencipta aksara dan asal tulisan dengan lebih jelas."
    },
    {
      "seq_in_article": 51,
      "pinyin": "wàn wù fēn lèi shì lǐ jiě cāng jié zào zì hé wén zì qǐ yuán de zhòng yào shén huà huà miàn",
      "content_zh": "万物分类是理解仓颉造字和文字起源的重要神话画面。",
      "content_en": "classifying all things is an important mythic image for understanding Cangjie creating characters and writing origins.",
      "content_vi": "Phần này là điểm quan trọng để hiểu Thương Hiệt tạo chữ và nguồn gốc chữ viết.",
      "content_th": "ส่วนนี้เป็นจุดสำคัญในการเข้าใจชางเจี๋ยสร้างอักษรกับต้นกำเนิดตัวเขียน",
      "content_id": "Bagian ini penting untuk memahami Cangjie mencipta aksara dan asal tulisan."
    },
    {
      "seq_in_article": 52,
      "pinyin": "tā bǎ cāng jié zào zì hé wén zì qǐ yuán fàng huí tiān dì qǐ yuán zì rán biàn huà hé rén lèi shēng huó xiǎng xiàng zhī zhōng",
      "content_zh": "它把仓颉造字和文字起源放回天地起源、自然变化和人类生活想象之中。",
      "content_en": "It places Cangjie creating characters and writing origins back into origins, natural change, and imagination about human life.",
      "content_vi": "Nó đặt Thương Hiệt tạo chữ và nguồn gốc chữ viết trở lại trong bối cảnh không gian, ký hiệu và đời sống.",
      "content_th": "มันพาชางเจี๋ยสร้างอักษรกับต้นกำเนิดตัวเขียนกลับไปอยู่ในบริบทของพื้นที่ สัญลักษณ์ และชีวิตจริง",
      "content_id": "Ia menempatkan Cangjie mencipta aksara dan asal tulisan kembali dalam konteks ruang, simbol, dan kehidupan nyata."
    },
    {
      "seq_in_article": 53,
      "pinyin": "shén huà bìng bù děng tóng yú shì shí jì lù ér shì yòng gù shì biǎo dá gǔ rén miàn duì shì jiè shí de lǐ jiě fāng shì",
      "content_zh": "神话并不等同于事实记录，而是用故事表达古人面对世界时的理解方式。",
      "content_en": "Myth is not the same as factual record; it uses stories to express how ancient people understood the world.",
      "content_vi": "Hình ảnh, thao tác, công cụ và thói quen cùng tạo nên kinh nghiệm có thể quan sát.",
      "content_th": "ภาพ การกระทำ เครื่องมือ และความเคยชินร่วมกันสร้างประสบการณ์ที่สังเกตได้",
      "content_id": "Gambar, tindakan, alat, dan kebiasaan bersama membentuk pengalaman yang dapat diamati."
    },
    {
      "seq_in_article": 54,
      "pinyin": "rén wù shén lì zāi hài hé xiū fù xíng dòng cháng bèi fàng zài tóng yí duàn xù shì lǐ xíng chéng qiáng liè huà miàn",
      "content_zh": "人物、神力、灾害和修复行动常被放在同一段叙事里，形成强烈画面。",
      "content_en": "Figures, divine power, disasters, and repair actions often appear together and create vivid images.",
      "content_vi": "Những thay đổi nhỏ trong đời thường thường cho thấy cách xã hội vận hành.",
      "content_th": "การเปลี่ยนเล็กๆ ในชีวิตประจำวันมักเผยให้เห็นวิธีที่สังคมทำงาน",
      "content_id": "Perubahan kecil dalam keseharian sering memperlihatkan cara masyarakat bekerja."
    },
    {
      "seq_in_article": 55,
      "pinyin": "rú guǒ zhī jì zhù míng zì rén men róng yì hū lüè gù shì bèi hòu de zì rán guān chá hé shēng huó yuàn wàng",
      "content_zh": "如果只记住名字，人们容易忽略故事背后的自然观察和生活愿望。",
      "content_en": "If people only remember names, they may miss the natural observation and life wishes behind the stories.",
      "content_vi": "Nếu chỉ nhớ tên gọi, người học dễ bỏ qua bối cảnh và cách dùng cụ thể.",
      "content_th": "หากจำเพียงชื่อ ผู้เรียนอาจมองข้ามบริบทและวิธีใช้ที่เฉพาะเจาะจง",
      "content_id": "Jika hanya mengingat nama, pelajar mudah melewatkan konteks dan cara pakai konkret."
    },
    {
      "seq_in_article": 56,
      "pinyin": "wàn wù fēn lèi yě shuō míng shén huà cháng yòng kuā zhāng xíng xiàng huí dá qǐ yuán zhì xù hé shēng cún wèn tí",
      "content_zh": "万物分类也说明，神话常用夸张形象回答起源、秩序和生存问题。",
      "content_en": "classifying all things also shows how myths use exaggerated images to answer questions of origin, order, and survival.",
      "content_vi": "Điều đó cho thấy Thương Hiệt tạo chữ và nguồn gốc chữ viết được hình thành từ nhiều lớp kinh nghiệm lâu dài.",
      "content_th": "สิ่งนี้แสดงว่าชางเจี๋ยสร้างอักษรกับต้นกำเนิดตัวเขียนเกิดจากประสบการณ์ยาวนานหลายชั้น",
      "content_id": "Hal ini menunjukkan bahwa Cangjie mencipta aksara dan asal tulisan dibentuk oleh banyak lapisan pengalaman panjang."
    },
    {
      "seq_in_article": 57,
      "pinyin": "zhè xiē gù shì tōng guò kǒu tóu jiǎng shù tú xiàng jié rì hé ér tóng dú wù bú duàn liú chuán",
      "content_zh": "这些故事通过口头讲述、图像、节日和儿童读物不断流传。",
      "content_en": "These stories continue through oral telling, images, festivals, and children’s books.",
      "content_vi": "Nội dung này tiếp tục truyền qua lớp học, truyền thông, gia đình và quan sát hằng ngày.",
      "content_th": "เนื้อหานี้ยังส่งต่อผ่านห้องเรียน สื่อ ครอบครัว และการสังเกตประจำวัน",
      "content_id": "Isi ini terus diwariskan melalui kelas, media, keluarga, dan pengamatan harian."
    },
    {
      "seq_in_article": 58,
      "pinyin": "dāng dài lǐ jiě shén huà shí kě yǐ tóng shí kàn dào xiǎng xiàng lì xiàng zhēng yì yì hé wén huà jì yì",
      "content_zh": "当代理解神话时，可以同时看到想象力、象征意义和文化记忆。",
      "content_en": "Modern understanding of myth can see imagination, symbolism, and cultural memory at the same time.",
      "content_vi": "Trong đời sống hiện đại, cần hiểu nghĩa cũ rồi so sánh với tình huống mới.",
      "content_th": "ในชีวิตสมัยใหม่ ควรเข้าใจความหมายเดิมแล้วเปรียบกับสถานการณ์ใหม่",
      "content_id": "Dalam kehidupan modern, makna lama perlu dipahami lalu dibandingkan dengan keadaan baru."
    },
    {
      "seq_in_article": 59,
      "pinyin": "bǎ jué sè qíng jié hé jiě shì gōng néng lián qǐ lái shén huà jiù bù zhǐ shì qí yì gù shì",
      "content_zh": "把角色、情节和解释功能连起来，神话就不只是奇异故事。",
      "content_en": "When roles, plots, and explanatory functions are connected, myths are more than strange tales.",
      "content_vi": "Khi đặt hình ảnh, hành động và ý nghĩa cạnh nhau, truyền thống trở nên gần hơn.",
      "content_th": "เมื่อนำภาพ การกระทำ และความหมายมาไว้ด้วยกัน ประเพณีจะใกล้ตัวขึ้น",
      "content_id": "Ketika gambar, tindakan, dan makna ditempatkan bersama, tradisi menjadi lebih dekat."
    },
    {
      "seq_in_article": 60,
      "pinyin": "yīn cǐ wàn wù fēn lèi bù jǐn shì chuán shuō nèi róng yě bāng zhù rén men lǐ jiě cāng jié zào zì hé wén zì qǐ yuán",
      "content_zh": "因此，万物分类不仅是传说内容，也帮助人们理解仓颉造字和文字起源。",
      "content_en": "Therefore, classifying all things is not only legend content but also a way to understand Cangjie creating characters and writing origins.",
      "content_vi": "Vì vậy, nội dung này giúp người học hôm nay hiểu Thương Hiệt tạo chữ và nguồn gốc chữ viết rõ hơn.",
      "content_th": "ดังนั้นเนื้อหานี้ช่วยให้ผู้เรียนวันนี้เข้าใจชางเจี๋ยสร้างอักษรกับต้นกำเนิดตัวเขียนได้ชัดเจนขึ้น",
      "content_id": "Karena itu, bagian ini membantu pelajar masa kini memahami Cangjie mencipta aksara dan asal tulisan dengan lebih jelas."
    },
    {
      "seq_in_article": 61,
      "pinyin": "jì lù néng lì shì lǐ jiě cāng jié zào zì hé wén zì qǐ yuán de zhòng yào shén huà huà miàn",
      "content_zh": "记录能力是理解仓颉造字和文字起源的重要神话画面。",
      "content_en": "recording ability is an important mythic image for understanding Cangjie creating characters and writing origins.",
      "content_vi": "Phần này là điểm quan trọng để hiểu Thương Hiệt tạo chữ và nguồn gốc chữ viết.",
      "content_th": "ส่วนนี้เป็นจุดสำคัญในการเข้าใจชางเจี๋ยสร้างอักษรกับต้นกำเนิดตัวเขียน",
      "content_id": "Bagian ini penting untuk memahami Cangjie mencipta aksara dan asal tulisan."
    },
    {
      "seq_in_article": 62,
      "pinyin": "tā bǎ cāng jié zào zì hé wén zì qǐ yuán fàng huí tiān dì qǐ yuán zì rán biàn huà hé rén lèi shēng huó xiǎng xiàng zhī zhōng",
      "content_zh": "它把仓颉造字和文字起源放回天地起源、自然变化和人类生活想象之中。",
      "content_en": "It places Cangjie creating characters and writing origins back into origins, natural change, and imagination about human life.",
      "content_vi": "Nó đặt Thương Hiệt tạo chữ và nguồn gốc chữ viết trở lại trong bối cảnh không gian, ký hiệu và đời sống.",
      "content_th": "มันพาชางเจี๋ยสร้างอักษรกับต้นกำเนิดตัวเขียนกลับไปอยู่ในบริบทของพื้นที่ สัญลักษณ์ และชีวิตจริง",
      "content_id": "Ia menempatkan Cangjie mencipta aksara dan asal tulisan kembali dalam konteks ruang, simbol, dan kehidupan nyata."
    },
    {
      "seq_in_article": 63,
      "pinyin": "shén huà bìng bù děng tóng yú shì shí jì lù ér shì yòng gù shì biǎo dá gǔ rén miàn duì shì jiè shí de lǐ jiě fāng shì",
      "content_zh": "神话并不等同于事实记录，而是用故事表达古人面对世界时的理解方式。",
      "content_en": "Myth is not the same as factual record; it uses stories to express how ancient people understood the world.",
      "content_vi": "Hình ảnh, thao tác, công cụ và thói quen cùng tạo nên kinh nghiệm có thể quan sát.",
      "content_th": "ภาพ การกระทำ เครื่องมือ และความเคยชินร่วมกันสร้างประสบการณ์ที่สังเกตได้",
      "content_id": "Gambar, tindakan, alat, dan kebiasaan bersama membentuk pengalaman yang dapat diamati."
    },
    {
      "seq_in_article": 64,
      "pinyin": "rén wù shén lì zāi hài hé xiū fù xíng dòng cháng bèi fàng zài tóng yí duàn xù shì lǐ xíng chéng qiáng liè huà miàn",
      "content_zh": "人物、神力、灾害和修复行动常被放在同一段叙事里，形成强烈画面。",
      "content_en": "Figures, divine power, disasters, and repair actions often appear together and create vivid images.",
      "content_vi": "Những thay đổi nhỏ trong đời thường thường cho thấy cách xã hội vận hành.",
      "content_th": "การเปลี่ยนเล็กๆ ในชีวิตประจำวันมักเผยให้เห็นวิธีที่สังคมทำงาน",
      "content_id": "Perubahan kecil dalam keseharian sering memperlihatkan cara masyarakat bekerja."
    },
    {
      "seq_in_article": 65,
      "pinyin": "rú guǒ zhī jì zhù míng zì rén men róng yì hū lüè gù shì bèi hòu de zì rán guān chá hé shēng huó yuàn wàng",
      "content_zh": "如果只记住名字，人们容易忽略故事背后的自然观察和生活愿望。",
      "content_en": "If people only remember names, they may miss the natural observation and life wishes behind the stories.",
      "content_vi": "Nếu chỉ nhớ tên gọi, người học dễ bỏ qua bối cảnh và cách dùng cụ thể.",
      "content_th": "หากจำเพียงชื่อ ผู้เรียนอาจมองข้ามบริบทและวิธีใช้ที่เฉพาะเจาะจง",
      "content_id": "Jika hanya mengingat nama, pelajar mudah melewatkan konteks dan cara pakai konkret."
    },
    {
      "seq_in_article": 66,
      "pinyin": "jì lù néng lì yě shuō míng shén huà cháng yòng kuā zhāng xíng xiàng huí dá qǐ yuán zhì xù hé shēng cún wèn tí",
      "content_zh": "记录能力也说明，神话常用夸张形象回答起源、秩序和生存问题。",
      "content_en": "recording ability also shows how myths use exaggerated images to answer questions of origin, order, and survival.",
      "content_vi": "Điều đó cho thấy Thương Hiệt tạo chữ và nguồn gốc chữ viết được hình thành từ nhiều lớp kinh nghiệm lâu dài.",
      "content_th": "สิ่งนี้แสดงว่าชางเจี๋ยสร้างอักษรกับต้นกำเนิดตัวเขียนเกิดจากประสบการณ์ยาวนานหลายชั้น",
      "content_id": "Hal ini menunjukkan bahwa Cangjie mencipta aksara dan asal tulisan dibentuk oleh banyak lapisan pengalaman panjang."
    },
    {
      "seq_in_article": 67,
      "pinyin": "zhè xiē gù shì tōng guò kǒu tóu jiǎng shù tú xiàng jié rì hé ér tóng dú wù bú duàn liú chuán",
      "content_zh": "这些故事通过口头讲述、图像、节日和儿童读物不断流传。",
      "content_en": "These stories continue through oral telling, images, festivals, and children’s books.",
      "content_vi": "Nội dung này tiếp tục truyền qua lớp học, truyền thông, gia đình và quan sát hằng ngày.",
      "content_th": "เนื้อหานี้ยังส่งต่อผ่านห้องเรียน สื่อ ครอบครัว และการสังเกตประจำวัน",
      "content_id": "Isi ini terus diwariskan melalui kelas, media, keluarga, dan pengamatan harian."
    },
    {
      "seq_in_article": 68,
      "pinyin": "dāng dài lǐ jiě shén huà shí kě yǐ tóng shí kàn dào xiǎng xiàng lì xiàng zhēng yì yì hé wén huà jì yì",
      "content_zh": "当代理解神话时，可以同时看到想象力、象征意义和文化记忆。",
      "content_en": "Modern understanding of myth can see imagination, symbolism, and cultural memory at the same time.",
      "content_vi": "Trong đời sống hiện đại, cần hiểu nghĩa cũ rồi so sánh với tình huống mới.",
      "content_th": "ในชีวิตสมัยใหม่ ควรเข้าใจความหมายเดิมแล้วเปรียบกับสถานการณ์ใหม่",
      "content_id": "Dalam kehidupan modern, makna lama perlu dipahami lalu dibandingkan dengan keadaan baru."
    },
    {
      "seq_in_article": 69,
      "pinyin": "bǎ jué sè qíng jié hé jiě shì gōng néng lián qǐ lái shén huà jiù bù zhǐ shì qí yì gù shì",
      "content_zh": "把角色、情节和解释功能连起来，神话就不只是奇异故事。",
      "content_en": "When roles, plots, and explanatory functions are connected, myths are more than strange tales.",
      "content_vi": "Khi đặt hình ảnh, hành động và ý nghĩa cạnh nhau, truyền thống trở nên gần hơn.",
      "content_th": "เมื่อนำภาพ การกระทำ และความหมายมาไว้ด้วยกัน ประเพณีจะใกล้ตัวขึ้น",
      "content_id": "Ketika gambar, tindakan, dan makna ditempatkan bersama, tradisi menjadi lebih dekat."
    },
    {
      "seq_in_article": 70,
      "pinyin": "yīn cǐ jì lù néng lì bù jǐn shì chuán shuō nèi róng yě bāng zhù rén men lǐ jiě cāng jié zào zì hé wén zì qǐ yuán",
      "content_zh": "因此，记录能力不仅是传说内容，也帮助人们理解仓颉造字和文字起源。",
      "content_en": "Therefore, recording ability is not only legend content but also a way to understand Cangjie creating characters and writing origins.",
      "content_vi": "Vì vậy, nội dung này giúp người học hôm nay hiểu Thương Hiệt tạo chữ và nguồn gốc chữ viết rõ hơn.",
      "content_th": "ดังนั้นเนื้อหานี้ช่วยให้ผู้เรียนวันนี้เข้าใจชางเจี๋ยสร้างอักษรกับต้นกำเนิดตัวเขียนได้ชัดเจนขึ้น",
      "content_id": "Karena itu, bagian ini membantu pelajar masa kini memahami Cangjie mencipta aksara dan asal tulisan dengan lebih jelas."
    },
    {
      "seq_in_article": 71,
      "pinyin": "shén qí fǎn yìng shì lǐ jiě cāng jié zào zì hé wén zì qǐ yuán de zhòng yào shén huà huà miàn",
      "content_zh": "神奇反应是理解仓颉造字和文字起源的重要神话画面。",
      "content_en": "marvelous reaction is an important mythic image for understanding Cangjie creating characters and writing origins.",
      "content_vi": "Phần này là điểm quan trọng để hiểu Thương Hiệt tạo chữ và nguồn gốc chữ viết.",
      "content_th": "ส่วนนี้เป็นจุดสำคัญในการเข้าใจชางเจี๋ยสร้างอักษรกับต้นกำเนิดตัวเขียน",
      "content_id": "Bagian ini penting untuk memahami Cangjie mencipta aksara dan asal tulisan."
    },
    {
      "seq_in_article": 72,
      "pinyin": "tā bǎ cāng jié zào zì hé wén zì qǐ yuán fàng huí tiān dì qǐ yuán zì rán biàn huà hé rén lèi shēng huó xiǎng xiàng zhī zhōng",
      "content_zh": "它把仓颉造字和文字起源放回天地起源、自然变化和人类生活想象之中。",
      "content_en": "It places Cangjie creating characters and writing origins back into origins, natural change, and imagination about human life.",
      "content_vi": "Nó đặt Thương Hiệt tạo chữ và nguồn gốc chữ viết trở lại trong bối cảnh không gian, ký hiệu và đời sống.",
      "content_th": "มันพาชางเจี๋ยสร้างอักษรกับต้นกำเนิดตัวเขียนกลับไปอยู่ในบริบทของพื้นที่ สัญลักษณ์ และชีวิตจริง",
      "content_id": "Ia menempatkan Cangjie mencipta aksara dan asal tulisan kembali dalam konteks ruang, simbol, dan kehidupan nyata."
    },
    {
      "seq_in_article": 73,
      "pinyin": "shén huà bìng bù děng tóng yú shì shí jì lù ér shì yòng gù shì biǎo dá gǔ rén miàn duì shì jiè shí de lǐ jiě fāng shì",
      "content_zh": "神话并不等同于事实记录，而是用故事表达古人面对世界时的理解方式。",
      "content_en": "Myth is not the same as factual record; it uses stories to express how ancient people understood the world.",
      "content_vi": "Hình ảnh, thao tác, công cụ và thói quen cùng tạo nên kinh nghiệm có thể quan sát.",
      "content_th": "ภาพ การกระทำ เครื่องมือ และความเคยชินร่วมกันสร้างประสบการณ์ที่สังเกตได้",
      "content_id": "Gambar, tindakan, alat, dan kebiasaan bersama membentuk pengalaman yang dapat diamati."
    },
    {
      "seq_in_article": 74,
      "pinyin": "rén wù shén lì zāi hài hé xiū fù xíng dòng cháng bèi fàng zài tóng yí duàn xù shì lǐ xíng chéng qiáng liè huà miàn",
      "content_zh": "人物、神力、灾害和修复行动常被放在同一段叙事里，形成强烈画面。",
      "content_en": "Figures, divine power, disasters, and repair actions often appear together and create vivid images.",
      "content_vi": "Những thay đổi nhỏ trong đời thường thường cho thấy cách xã hội vận hành.",
      "content_th": "การเปลี่ยนเล็กๆ ในชีวิตประจำวันมักเผยให้เห็นวิธีที่สังคมทำงาน",
      "content_id": "Perubahan kecil dalam keseharian sering memperlihatkan cara masyarakat bekerja."
    },
    {
      "seq_in_article": 75,
      "pinyin": "rú guǒ zhī jì zhù míng zì rén men róng yì hū lüè gù shì bèi hòu de zì rán guān chá hé shēng huó yuàn wàng",
      "content_zh": "如果只记住名字，人们容易忽略故事背后的自然观察和生活愿望。",
      "content_en": "If people only remember names, they may miss the natural observation and life wishes behind the stories.",
      "content_vi": "Nếu chỉ nhớ tên gọi, người học dễ bỏ qua bối cảnh và cách dùng cụ thể.",
      "content_th": "หากจำเพียงชื่อ ผู้เรียนอาจมองข้ามบริบทและวิธีใช้ที่เฉพาะเจาะจง",
      "content_id": "Jika hanya mengingat nama, pelajar mudah melewatkan konteks dan cara pakai konkret."
    },
    {
      "seq_in_article": 76,
      "pinyin": "shén qí fǎn yìng yě shuō míng shén huà cháng yòng kuā zhāng xíng xiàng huí dá qǐ yuán zhì xù hé shēng cún wèn tí",
      "content_zh": "神奇反应也说明，神话常用夸张形象回答起源、秩序和生存问题。",
      "content_en": "marvelous reaction also shows how myths use exaggerated images to answer questions of origin, order, and survival.",
      "content_vi": "Điều đó cho thấy Thương Hiệt tạo chữ và nguồn gốc chữ viết được hình thành từ nhiều lớp kinh nghiệm lâu dài.",
      "content_th": "สิ่งนี้แสดงว่าชางเจี๋ยสร้างอักษรกับต้นกำเนิดตัวเขียนเกิดจากประสบการณ์ยาวนานหลายชั้น",
      "content_id": "Hal ini menunjukkan bahwa Cangjie mencipta aksara dan asal tulisan dibentuk oleh banyak lapisan pengalaman panjang."
    },
    {
      "seq_in_article": 77,
      "pinyin": "zhè xiē gù shì tōng guò kǒu tóu jiǎng shù tú xiàng jié rì hé ér tóng dú wù bú duàn liú chuán",
      "content_zh": "这些故事通过口头讲述、图像、节日和儿童读物不断流传。",
      "content_en": "These stories continue through oral telling, images, festivals, and children’s books.",
      "content_vi": "Nội dung này tiếp tục truyền qua lớp học, truyền thông, gia đình và quan sát hằng ngày.",
      "content_th": "เนื้อหานี้ยังส่งต่อผ่านห้องเรียน สื่อ ครอบครัว และการสังเกตประจำวัน",
      "content_id": "Isi ini terus diwariskan melalui kelas, media, keluarga, dan pengamatan harian."
    },
    {
      "seq_in_article": 78,
      "pinyin": "dāng dài lǐ jiě shén huà shí kě yǐ tóng shí kàn dào xiǎng xiàng lì xiàng zhēng yì yì hé wén huà jì yì",
      "content_zh": "当代理解神话时，可以同时看到想象力、象征意义和文化记忆。",
      "content_en": "Modern understanding of myth can see imagination, symbolism, and cultural memory at the same time.",
      "content_vi": "Trong đời sống hiện đại, cần hiểu nghĩa cũ rồi so sánh với tình huống mới.",
      "content_th": "ในชีวิตสมัยใหม่ ควรเข้าใจความหมายเดิมแล้วเปรียบกับสถานการณ์ใหม่",
      "content_id": "Dalam kehidupan modern, makna lama perlu dipahami lalu dibandingkan dengan keadaan baru."
    },
    {
      "seq_in_article": 79,
      "pinyin": "bǎ jué sè qíng jié hé jiě shì gōng néng lián qǐ lái shén huà jiù bù zhǐ shì qí yì gù shì",
      "content_zh": "把角色、情节和解释功能连起来，神话就不只是奇异故事。",
      "content_en": "When roles, plots, and explanatory functions are connected, myths are more than strange tales.",
      "content_vi": "Khi đặt hình ảnh, hành động và ý nghĩa cạnh nhau, truyền thống trở nên gần hơn.",
      "content_th": "เมื่อนำภาพ การกระทำ และความหมายมาไว้ด้วยกัน ประเพณีจะใกล้ตัวขึ้น",
      "content_id": "Ketika gambar, tindakan, dan makna ditempatkan bersama, tradisi menjadi lebih dekat."
    },
    {
      "seq_in_article": 80,
      "pinyin": "yīn cǐ shén qí fǎn yìng bù jǐn shì chuán shuō nèi róng yě bāng zhù rén men lǐ jiě cāng jié zào zì hé wén zì qǐ yuán",
      "content_zh": "因此，神奇反应不仅是传说内容，也帮助人们理解仓颉造字和文字起源。",
      "content_en": "Therefore, marvelous reaction is not only legend content but also a way to understand Cangjie creating characters and writing origins.",
      "content_vi": "Vì vậy, nội dung này giúp người học hôm nay hiểu Thương Hiệt tạo chữ và nguồn gốc chữ viết rõ hơn.",
      "content_th": "ดังนั้นเนื้อหานี้ช่วยให้ผู้เรียนวันนี้เข้าใจชางเจี๋ยสร้างอักษรกับต้นกำเนิดตัวเขียนได้ชัดเจนขึ้น",
      "content_id": "Karena itu, bagian ini membantu pelajar masa kini memahami Cangjie mencipta aksara dan asal tulisan dengan lebih jelas."
    },
    {
      "seq_in_article": 81,
      "pinyin": "huáng dì guān lián shì lǐ jiě cāng jié zào zì hé wén zì qǐ yuán de zhòng yào shén huà huà miàn",
      "content_zh": "黄帝关联是理解仓颉造字和文字起源的重要神话画面。",
      "content_en": "Yellow Emperor link is an important mythic image for understanding Cangjie creating characters and writing origins.",
      "content_vi": "Phần này là điểm quan trọng để hiểu Thương Hiệt tạo chữ và nguồn gốc chữ viết.",
      "content_th": "ส่วนนี้เป็นจุดสำคัญในการเข้าใจชางเจี๋ยสร้างอักษรกับต้นกำเนิดตัวเขียน",
      "content_id": "Bagian ini penting untuk memahami Cangjie mencipta aksara dan asal tulisan."
    },
    {
      "seq_in_article": 82,
      "pinyin": "tā bǎ cāng jié zào zì hé wén zì qǐ yuán fàng huí tiān dì qǐ yuán zì rán biàn huà hé rén lèi shēng huó xiǎng xiàng zhī zhōng",
      "content_zh": "它把仓颉造字和文字起源放回天地起源、自然变化和人类生活想象之中。",
      "content_en": "It places Cangjie creating characters and writing origins back into origins, natural change, and imagination about human life.",
      "content_vi": "Nó đặt Thương Hiệt tạo chữ và nguồn gốc chữ viết trở lại trong bối cảnh không gian, ký hiệu và đời sống.",
      "content_th": "มันพาชางเจี๋ยสร้างอักษรกับต้นกำเนิดตัวเขียนกลับไปอยู่ในบริบทของพื้นที่ สัญลักษณ์ และชีวิตจริง",
      "content_id": "Ia menempatkan Cangjie mencipta aksara dan asal tulisan kembali dalam konteks ruang, simbol, dan kehidupan nyata."
    },
    {
      "seq_in_article": 83,
      "pinyin": "shén huà bìng bù děng tóng yú shì shí jì lù ér shì yòng gù shì biǎo dá gǔ rén miàn duì shì jiè shí de lǐ jiě fāng shì",
      "content_zh": "神话并不等同于事实记录，而是用故事表达古人面对世界时的理解方式。",
      "content_en": "Myth is not the same as factual record; it uses stories to express how ancient people understood the world.",
      "content_vi": "Hình ảnh, thao tác, công cụ và thói quen cùng tạo nên kinh nghiệm có thể quan sát.",
      "content_th": "ภาพ การกระทำ เครื่องมือ และความเคยชินร่วมกันสร้างประสบการณ์ที่สังเกตได้",
      "content_id": "Gambar, tindakan, alat, dan kebiasaan bersama membentuk pengalaman yang dapat diamati."
    },
    {
      "seq_in_article": 84,
      "pinyin": "rén wù shén lì zāi hài hé xiū fù xíng dòng cháng bèi fàng zài tóng yí duàn xù shì lǐ xíng chéng qiáng liè huà miàn",
      "content_zh": "人物、神力、灾害和修复行动常被放在同一段叙事里，形成强烈画面。",
      "content_en": "Figures, divine power, disasters, and repair actions often appear together and create vivid images.",
      "content_vi": "Những thay đổi nhỏ trong đời thường thường cho thấy cách xã hội vận hành.",
      "content_th": "การเปลี่ยนเล็กๆ ในชีวิตประจำวันมักเผยให้เห็นวิธีที่สังคมทำงาน",
      "content_id": "Perubahan kecil dalam keseharian sering memperlihatkan cara masyarakat bekerja."
    },
    {
      "seq_in_article": 85,
      "pinyin": "rú guǒ zhī jì zhù míng zì rén men róng yì hū lüè gù shì bèi hòu de zì rán guān chá hé shēng huó yuàn wàng",
      "content_zh": "如果只记住名字，人们容易忽略故事背后的自然观察和生活愿望。",
      "content_en": "If people only remember names, they may miss the natural observation and life wishes behind the stories.",
      "content_vi": "Nếu chỉ nhớ tên gọi, người học dễ bỏ qua bối cảnh và cách dùng cụ thể.",
      "content_th": "หากจำเพียงชื่อ ผู้เรียนอาจมองข้ามบริบทและวิธีใช้ที่เฉพาะเจาะจง",
      "content_id": "Jika hanya mengingat nama, pelajar mudah melewatkan konteks dan cara pakai konkret."
    },
    {
      "seq_in_article": 86,
      "pinyin": "huáng dì guān lián yě shuō míng shén huà cháng yòng kuā zhāng xíng xiàng huí dá qǐ yuán zhì xù hé shēng cún wèn tí",
      "content_zh": "黄帝关联也说明，神话常用夸张形象回答起源、秩序和生存问题。",
      "content_en": "Yellow Emperor link also shows how myths use exaggerated images to answer questions of origin, order, and survival.",
      "content_vi": "Điều đó cho thấy Thương Hiệt tạo chữ và nguồn gốc chữ viết được hình thành từ nhiều lớp kinh nghiệm lâu dài.",
      "content_th": "สิ่งนี้แสดงว่าชางเจี๋ยสร้างอักษรกับต้นกำเนิดตัวเขียนเกิดจากประสบการณ์ยาวนานหลายชั้น",
      "content_id": "Hal ini menunjukkan bahwa Cangjie mencipta aksara dan asal tulisan dibentuk oleh banyak lapisan pengalaman panjang."
    },
    {
      "seq_in_article": 87,
      "pinyin": "zhè xiē gù shì tōng guò kǒu tóu jiǎng shù tú xiàng jié rì hé ér tóng dú wù bú duàn liú chuán",
      "content_zh": "这些故事通过口头讲述、图像、节日和儿童读物不断流传。",
      "content_en": "These stories continue through oral telling, images, festivals, and children’s books.",
      "content_vi": "Nội dung này tiếp tục truyền qua lớp học, truyền thông, gia đình và quan sát hằng ngày.",
      "content_th": "เนื้อหานี้ยังส่งต่อผ่านห้องเรียน สื่อ ครอบครัว และการสังเกตประจำวัน",
      "content_id": "Isi ini terus diwariskan melalui kelas, media, keluarga, dan pengamatan harian."
    },
    {
      "seq_in_article": 88,
      "pinyin": "dāng dài lǐ jiě shén huà shí kě yǐ tóng shí kàn dào xiǎng xiàng lì xiàng zhēng yì yì hé wén huà jì yì",
      "content_zh": "当代理解神话时，可以同时看到想象力、象征意义和文化记忆。",
      "content_en": "Modern understanding of myth can see imagination, symbolism, and cultural memory at the same time.",
      "content_vi": "Trong đời sống hiện đại, cần hiểu nghĩa cũ rồi so sánh với tình huống mới.",
      "content_th": "ในชีวิตสมัยใหม่ ควรเข้าใจความหมายเดิมแล้วเปรียบกับสถานการณ์ใหม่",
      "content_id": "Dalam kehidupan modern, makna lama perlu dipahami lalu dibandingkan dengan keadaan baru."
    },
    {
      "seq_in_article": 89,
      "pinyin": "bǎ jué sè qíng jié hé jiě shì gōng néng lián qǐ lái shén huà jiù bù zhǐ shì qí yì gù shì",
      "content_zh": "把角色、情节和解释功能连起来，神话就不只是奇异故事。",
      "content_en": "When roles, plots, and explanatory functions are connected, myths are more than strange tales.",
      "content_vi": "Khi đặt hình ảnh, hành động và ý nghĩa cạnh nhau, truyền thống trở nên gần hơn.",
      "content_th": "เมื่อนำภาพ การกระทำ และความหมายมาไว้ด้วยกัน ประเพณีจะใกล้ตัวขึ้น",
      "content_id": "Ketika gambar, tindakan, dan makna ditempatkan bersama, tradisi menjadi lebih dekat."
    },
    {
      "seq_in_article": 90,
      "pinyin": "yīn cǐ huáng dì guān lián bù jǐn shì chuán shuō nèi róng yě bāng zhù rén men lǐ jiě cāng jié zào zì hé wén zì qǐ yuán",
      "content_zh": "因此，黄帝关联不仅是传说内容，也帮助人们理解仓颉造字和文字起源。",
      "content_en": "Therefore, Yellow Emperor link is not only legend content but also a way to understand Cangjie creating characters and writing origins.",
      "content_vi": "Vì vậy, nội dung này giúp người học hôm nay hiểu Thương Hiệt tạo chữ và nguồn gốc chữ viết rõ hơn.",
      "content_th": "ดังนั้นเนื้อหานี้ช่วยให้ผู้เรียนวันนี้เข้าใจชางเจี๋ยสร้างอักษรกับต้นกำเนิดตัวเขียนได้ชัดเจนขึ้น",
      "content_id": "Karena itu, bagian ini membantu pelajar masa kini memahami Cangjie mencipta aksara dan asal tulisan dengan lebih jelas."
    },
    {
      "seq_in_article": 91,
      "pinyin": "hàn zì jì yì shì lǐ jiě cāng jié zào zì hé wén zì qǐ yuán de zhòng yào shén huà huà miàn",
      "content_zh": "汉字记忆是理解仓颉造字和文字起源的重要神话画面。",
      "content_en": "Hanzi memory is an important mythic image for understanding Cangjie creating characters and writing origins.",
      "content_vi": "Phần này là điểm quan trọng để hiểu Thương Hiệt tạo chữ và nguồn gốc chữ viết.",
      "content_th": "ส่วนนี้เป็นจุดสำคัญในการเข้าใจชางเจี๋ยสร้างอักษรกับต้นกำเนิดตัวเขียน",
      "content_id": "Bagian ini penting untuk memahami Cangjie mencipta aksara dan asal tulisan."
    },
    {
      "seq_in_article": 92,
      "pinyin": "tā bǎ cāng jié zào zì hé wén zì qǐ yuán fàng huí tiān dì qǐ yuán zì rán biàn huà hé rén lèi shēng huó xiǎng xiàng zhī zhōng",
      "content_zh": "它把仓颉造字和文字起源放回天地起源、自然变化和人类生活想象之中。",
      "content_en": "It places Cangjie creating characters and writing origins back into origins, natural change, and imagination about human life.",
      "content_vi": "Nó đặt Thương Hiệt tạo chữ và nguồn gốc chữ viết trở lại trong bối cảnh không gian, ký hiệu và đời sống.",
      "content_th": "มันพาชางเจี๋ยสร้างอักษรกับต้นกำเนิดตัวเขียนกลับไปอยู่ในบริบทของพื้นที่ สัญลักษณ์ และชีวิตจริง",
      "content_id": "Ia menempatkan Cangjie mencipta aksara dan asal tulisan kembali dalam konteks ruang, simbol, dan kehidupan nyata."
    },
    {
      "seq_in_article": 93,
      "pinyin": "shén huà bìng bù děng tóng yú shì shí jì lù ér shì yòng gù shì biǎo dá gǔ rén miàn duì shì jiè shí de lǐ jiě fāng shì",
      "content_zh": "神话并不等同于事实记录，而是用故事表达古人面对世界时的理解方式。",
      "content_en": "Myth is not the same as factual record; it uses stories to express how ancient people understood the world.",
      "content_vi": "Hình ảnh, thao tác, công cụ và thói quen cùng tạo nên kinh nghiệm có thể quan sát.",
      "content_th": "ภาพ การกระทำ เครื่องมือ และความเคยชินร่วมกันสร้างประสบการณ์ที่สังเกตได้",
      "content_id": "Gambar, tindakan, alat, dan kebiasaan bersama membentuk pengalaman yang dapat diamati."
    },
    {
      "seq_in_article": 94,
      "pinyin": "rén wù shén lì zāi hài hé xiū fù xíng dòng cháng bèi fàng zài tóng yí duàn xù shì lǐ xíng chéng qiáng liè huà miàn",
      "content_zh": "人物、神力、灾害和修复行动常被放在同一段叙事里，形成强烈画面。",
      "content_en": "Figures, divine power, disasters, and repair actions often appear together and create vivid images.",
      "content_vi": "Những thay đổi nhỏ trong đời thường thường cho thấy cách xã hội vận hành.",
      "content_th": "การเปลี่ยนเล็กๆ ในชีวิตประจำวันมักเผยให้เห็นวิธีที่สังคมทำงาน",
      "content_id": "Perubahan kecil dalam keseharian sering memperlihatkan cara masyarakat bekerja."
    },
    {
      "seq_in_article": 95,
      "pinyin": "rú guǒ zhī jì zhù míng zì rén men róng yì hū lüè gù shì bèi hòu de zì rán guān chá hé shēng huó yuàn wàng",
      "content_zh": "如果只记住名字，人们容易忽略故事背后的自然观察和生活愿望。",
      "content_en": "If people only remember names, they may miss the natural observation and life wishes behind the stories.",
      "content_vi": "Nếu chỉ nhớ tên gọi, người học dễ bỏ qua bối cảnh và cách dùng cụ thể.",
      "content_th": "หากจำเพียงชื่อ ผู้เรียนอาจมองข้ามบริบทและวิธีใช้ที่เฉพาะเจาะจง",
      "content_id": "Jika hanya mengingat nama, pelajar mudah melewatkan konteks dan cara pakai konkret."
    },
    {
      "seq_in_article": 96,
      "pinyin": "hàn zì jì yì yě shuō míng shén huà cháng yòng kuā zhāng xíng xiàng huí dá qǐ yuán zhì xù hé shēng cún wèn tí",
      "content_zh": "汉字记忆也说明，神话常用夸张形象回答起源、秩序和生存问题。",
      "content_en": "Hanzi memory also shows how myths use exaggerated images to answer questions of origin, order, and survival.",
      "content_vi": "Điều đó cho thấy Thương Hiệt tạo chữ và nguồn gốc chữ viết được hình thành từ nhiều lớp kinh nghiệm lâu dài.",
      "content_th": "สิ่งนี้แสดงว่าชางเจี๋ยสร้างอักษรกับต้นกำเนิดตัวเขียนเกิดจากประสบการณ์ยาวนานหลายชั้น",
      "content_id": "Hal ini menunjukkan bahwa Cangjie mencipta aksara dan asal tulisan dibentuk oleh banyak lapisan pengalaman panjang."
    },
    {
      "seq_in_article": 97,
      "pinyin": "zhè xiē gù shì tōng guò kǒu tóu jiǎng shù tú xiàng jié rì hé ér tóng dú wù bú duàn liú chuán",
      "content_zh": "这些故事通过口头讲述、图像、节日和儿童读物不断流传。",
      "content_en": "These stories continue through oral telling, images, festivals, and children’s books.",
      "content_vi": "Nội dung này tiếp tục truyền qua lớp học, truyền thông, gia đình và quan sát hằng ngày.",
      "content_th": "เนื้อหานี้ยังส่งต่อผ่านห้องเรียน สื่อ ครอบครัว และการสังเกตประจำวัน",
      "content_id": "Isi ini terus diwariskan melalui kelas, media, keluarga, dan pengamatan harian."
    },
    {
      "seq_in_article": 98,
      "pinyin": "dāng dài lǐ jiě shén huà shí kě yǐ tóng shí kàn dào xiǎng xiàng lì xiàng zhēng yì yì hé wén huà jì yì",
      "content_zh": "当代理解神话时，可以同时看到想象力、象征意义和文化记忆。",
      "content_en": "Modern understanding of myth can see imagination, symbolism, and cultural memory at the same time.",
      "content_vi": "Trong đời sống hiện đại, cần hiểu nghĩa cũ rồi so sánh với tình huống mới.",
      "content_th": "ในชีวิตสมัยใหม่ ควรเข้าใจความหมายเดิมแล้วเปรียบกับสถานการณ์ใหม่",
      "content_id": "Dalam kehidupan modern, makna lama perlu dipahami lalu dibandingkan dengan keadaan baru."
    },
    {
      "seq_in_article": 99,
      "pinyin": "bǎ jué sè qíng jié hé jiě shì gōng néng lián qǐ lái shén huà jiù bù zhǐ shì qí yì gù shì",
      "content_zh": "把角色、情节和解释功能连起来，神话就不只是奇异故事。",
      "content_en": "When roles, plots, and explanatory functions are connected, myths are more than strange tales.",
      "content_vi": "Khi đặt hình ảnh, hành động và ý nghĩa cạnh nhau, truyền thống trở nên gần hơn.",
      "content_th": "เมื่อนำภาพ การกระทำ และความหมายมาไว้ด้วยกัน ประเพณีจะใกล้ตัวขึ้น",
      "content_id": "Ketika gambar, tindakan, dan makna ditempatkan bersama, tradisi menjadi lebih dekat."
    },
    {
      "seq_in_article": 100,
      "pinyin": "yīn cǐ hàn zì jì yì bù jǐn shì chuán shuō nèi róng yě bāng zhù rén men lǐ jiě cāng jié zào zì hé wén zì qǐ yuán",
      "content_zh": "因此，汉字记忆不仅是传说内容，也帮助人们理解仓颉造字和文字起源。",
      "content_en": "Therefore, Hanzi memory is not only legend content but also a way to understand Cangjie creating characters and writing origins.",
      "content_vi": "Vì vậy, nội dung này giúp người học hôm nay hiểu Thương Hiệt tạo chữ và nguồn gốc chữ viết rõ hơn.",
      "content_th": "ดังนั้นเนื้อหานี้ช่วยให้ผู้เรียนวันนี้เข้าใจชางเจี๋ยสร้างอักษรกับต้นกำเนิดตัวเขียนได้ชัดเจนขึ้น",
      "content_id": "Karena itu, bagian ini membantu pelajar masa kini memahami Cangjie mencipta aksara dan asal tulisan dengan lebih jelas."
    },
    {
      "seq_in_article": 101,
      "pinyin": "wén huà jiě shì shì lǐ jiě cāng jié zào zì hé wén zì qǐ yuán de zhòng yào shén huà huà miàn",
      "content_zh": "文化解释是理解仓颉造字和文字起源的重要神话画面。",
      "content_en": "cultural explanation is an important mythic image for understanding Cangjie creating characters and writing origins.",
      "content_vi": "Phần này là điểm quan trọng để hiểu Thương Hiệt tạo chữ và nguồn gốc chữ viết.",
      "content_th": "ส่วนนี้เป็นจุดสำคัญในการเข้าใจชางเจี๋ยสร้างอักษรกับต้นกำเนิดตัวเขียน",
      "content_id": "Bagian ini penting untuk memahami Cangjie mencipta aksara dan asal tulisan."
    },
    {
      "seq_in_article": 102,
      "pinyin": "tā bǎ cāng jié zào zì hé wén zì qǐ yuán fàng huí tiān dì qǐ yuán zì rán biàn huà hé rén lèi shēng huó xiǎng xiàng zhī zhōng",
      "content_zh": "它把仓颉造字和文字起源放回天地起源、自然变化和人类生活想象之中。",
      "content_en": "It places Cangjie creating characters and writing origins back into origins, natural change, and imagination about human life.",
      "content_vi": "Nó đặt Thương Hiệt tạo chữ và nguồn gốc chữ viết trở lại trong bối cảnh không gian, ký hiệu và đời sống.",
      "content_th": "มันพาชางเจี๋ยสร้างอักษรกับต้นกำเนิดตัวเขียนกลับไปอยู่ในบริบทของพื้นที่ สัญลักษณ์ และชีวิตจริง",
      "content_id": "Ia menempatkan Cangjie mencipta aksara dan asal tulisan kembali dalam konteks ruang, simbol, dan kehidupan nyata."
    },
    {
      "seq_in_article": 103,
      "pinyin": "shén huà bìng bù děng tóng yú shì shí jì lù ér shì yòng gù shì biǎo dá gǔ rén miàn duì shì jiè shí de lǐ jiě fāng shì",
      "content_zh": "神话并不等同于事实记录，而是用故事表达古人面对世界时的理解方式。",
      "content_en": "Myth is not the same as factual record; it uses stories to express how ancient people understood the world.",
      "content_vi": "Hình ảnh, thao tác, công cụ và thói quen cùng tạo nên kinh nghiệm có thể quan sát.",
      "content_th": "ภาพ การกระทำ เครื่องมือ และความเคยชินร่วมกันสร้างประสบการณ์ที่สังเกตได้",
      "content_id": "Gambar, tindakan, alat, dan kebiasaan bersama membentuk pengalaman yang dapat diamati."
    },
    {
      "seq_in_article": 104,
      "pinyin": "rén wù shén lì zāi hài hé xiū fù xíng dòng cháng bèi fàng zài tóng yí duàn xù shì lǐ xíng chéng qiáng liè huà miàn",
      "content_zh": "人物、神力、灾害和修复行动常被放在同一段叙事里，形成强烈画面。",
      "content_en": "Figures, divine power, disasters, and repair actions often appear together and create vivid images.",
      "content_vi": "Những thay đổi nhỏ trong đời thường thường cho thấy cách xã hội vận hành.",
      "content_th": "การเปลี่ยนเล็กๆ ในชีวิตประจำวันมักเผยให้เห็นวิธีที่สังคมทำงาน",
      "content_id": "Perubahan kecil dalam keseharian sering memperlihatkan cara masyarakat bekerja."
    },
    {
      "seq_in_article": 105,
      "pinyin": "rú guǒ zhī jì zhù míng zì rén men róng yì hū lüè gù shì bèi hòu de zì rán guān chá hé shēng huó yuàn wàng",
      "content_zh": "如果只记住名字，人们容易忽略故事背后的自然观察和生活愿望。",
      "content_en": "If people only remember names, they may miss the natural observation and life wishes behind the stories.",
      "content_vi": "Nếu chỉ nhớ tên gọi, người học dễ bỏ qua bối cảnh và cách dùng cụ thể.",
      "content_th": "หากจำเพียงชื่อ ผู้เรียนอาจมองข้ามบริบทและวิธีใช้ที่เฉพาะเจาะจง",
      "content_id": "Jika hanya mengingat nama, pelajar mudah melewatkan konteks dan cara pakai konkret."
    },
    {
      "seq_in_article": 106,
      "pinyin": "wén huà jiě shì yě shuō míng shén huà cháng yòng kuā zhāng xíng xiàng huí dá qǐ yuán zhì xù hé shēng cún wèn tí",
      "content_zh": "文化解释也说明，神话常用夸张形象回答起源、秩序和生存问题。",
      "content_en": "cultural explanation also shows how myths use exaggerated images to answer questions of origin, order, and survival.",
      "content_vi": "Điều đó cho thấy Thương Hiệt tạo chữ và nguồn gốc chữ viết được hình thành từ nhiều lớp kinh nghiệm lâu dài.",
      "content_th": "สิ่งนี้แสดงว่าชางเจี๋ยสร้างอักษรกับต้นกำเนิดตัวเขียนเกิดจากประสบการณ์ยาวนานหลายชั้น",
      "content_id": "Hal ini menunjukkan bahwa Cangjie mencipta aksara dan asal tulisan dibentuk oleh banyak lapisan pengalaman panjang."
    },
    {
      "seq_in_article": 107,
      "pinyin": "zhè xiē gù shì tōng guò kǒu tóu jiǎng shù tú xiàng jié rì hé ér tóng dú wù bú duàn liú chuán",
      "content_zh": "这些故事通过口头讲述、图像、节日和儿童读物不断流传。",
      "content_en": "These stories continue through oral telling, images, festivals, and children’s books.",
      "content_vi": "Nội dung này tiếp tục truyền qua lớp học, truyền thông, gia đình và quan sát hằng ngày.",
      "content_th": "เนื้อหานี้ยังส่งต่อผ่านห้องเรียน สื่อ ครอบครัว และการสังเกตประจำวัน",
      "content_id": "Isi ini terus diwariskan melalui kelas, media, keluarga, dan pengamatan harian."
    },
    {
      "seq_in_article": 108,
      "pinyin": "dāng dài lǐ jiě shén huà shí kě yǐ tóng shí kàn dào xiǎng xiàng lì xiàng zhēng yì yì hé wén huà jì yì",
      "content_zh": "当代理解神话时，可以同时看到想象力、象征意义和文化记忆。",
      "content_en": "Modern understanding of myth can see imagination, symbolism, and cultural memory at the same time.",
      "content_vi": "Trong đời sống hiện đại, cần hiểu nghĩa cũ rồi so sánh với tình huống mới.",
      "content_th": "ในชีวิตสมัยใหม่ ควรเข้าใจความหมายเดิมแล้วเปรียบกับสถานการณ์ใหม่",
      "content_id": "Dalam kehidupan modern, makna lama perlu dipahami lalu dibandingkan dengan keadaan baru."
    },
    {
      "seq_in_article": 109,
      "pinyin": "bǎ jué sè qíng jié hé jiě shì gōng néng lián qǐ lái shén huà jiù bù zhǐ shì qí yì gù shì",
      "content_zh": "把角色、情节和解释功能连起来，神话就不只是奇异故事。",
      "content_en": "When roles, plots, and explanatory functions are connected, myths are more than strange tales.",
      "content_vi": "Khi đặt hình ảnh, hành động và ý nghĩa cạnh nhau, truyền thống trở nên gần hơn.",
      "content_th": "เมื่อนำภาพ การกระทำ และความหมายมาไว้ด้วยกัน ประเพณีจะใกล้ตัวขึ้น",
      "content_id": "Ketika gambar, tindakan, dan makna ditempatkan bersama, tradisi menjadi lebih dekat."
    },
    {
      "seq_in_article": 110,
      "pinyin": "yīn cǐ wén huà jiě shì bù jǐn shì chuán shuō nèi róng yě bāng zhù rén men lǐ jiě cāng jié zào zì hé wén zì qǐ yuán",
      "content_zh": "因此，文化解释不仅是传说内容，也帮助人们理解仓颉造字和文字起源。",
      "content_en": "Therefore, cultural explanation is not only legend content but also a way to understand Cangjie creating characters and writing origins.",
      "content_vi": "Vì vậy, nội dung này giúp người học hôm nay hiểu Thương Hiệt tạo chữ và nguồn gốc chữ viết rõ hơn.",
      "content_th": "ดังนั้นเนื้อหานี้ช่วยให้ผู้เรียนวันนี้เข้าใจชางเจี๋ยสร้างอักษรกับต้นกำเนิดตัวเขียนได้ชัดเจนขึ้น",
      "content_id": "Karena itu, bagian ini membantu pelajar masa kini memahami Cangjie mencipta aksara dan asal tulisan dengan lebih jelas."
    },
    {
      "seq_in_article": 111,
      "pinyin": "xué xí qù wèi shì lǐ jiě cāng jié zào zì hé wén zì qǐ yuán de zhòng yào shén huà huà miàn",
      "content_zh": "学习趣味是理解仓颉造字和文字起源的重要神话画面。",
      "content_en": "learning interest is an important mythic image for understanding Cangjie creating characters and writing origins.",
      "content_vi": "Phần này là điểm quan trọng để hiểu Thương Hiệt tạo chữ và nguồn gốc chữ viết.",
      "content_th": "ส่วนนี้เป็นจุดสำคัญในการเข้าใจชางเจี๋ยสร้างอักษรกับต้นกำเนิดตัวเขียน",
      "content_id": "Bagian ini penting untuk memahami Cangjie mencipta aksara dan asal tulisan."
    },
    {
      "seq_in_article": 112,
      "pinyin": "tā bǎ cāng jié zào zì hé wén zì qǐ yuán fàng huí tiān dì qǐ yuán zì rán biàn huà hé rén lèi shēng huó xiǎng xiàng zhī zhōng",
      "content_zh": "它把仓颉造字和文字起源放回天地起源、自然变化和人类生活想象之中。",
      "content_en": "It places Cangjie creating characters and writing origins back into origins, natural change, and imagination about human life.",
      "content_vi": "Nó đặt Thương Hiệt tạo chữ và nguồn gốc chữ viết trở lại trong bối cảnh không gian, ký hiệu và đời sống.",
      "content_th": "มันพาชางเจี๋ยสร้างอักษรกับต้นกำเนิดตัวเขียนกลับไปอยู่ในบริบทของพื้นที่ สัญลักษณ์ และชีวิตจริง",
      "content_id": "Ia menempatkan Cangjie mencipta aksara dan asal tulisan kembali dalam konteks ruang, simbol, dan kehidupan nyata."
    },
    {
      "seq_in_article": 113,
      "pinyin": "shén huà bìng bù děng tóng yú shì shí jì lù ér shì yòng gù shì biǎo dá gǔ rén miàn duì shì jiè shí de lǐ jiě fāng shì",
      "content_zh": "神话并不等同于事实记录，而是用故事表达古人面对世界时的理解方式。",
      "content_en": "Myth is not the same as factual record; it uses stories to express how ancient people understood the world.",
      "content_vi": "Hình ảnh, thao tác, công cụ và thói quen cùng tạo nên kinh nghiệm có thể quan sát.",
      "content_th": "ภาพ การกระทำ เครื่องมือ และความเคยชินร่วมกันสร้างประสบการณ์ที่สังเกตได้",
      "content_id": "Gambar, tindakan, alat, dan kebiasaan bersama membentuk pengalaman yang dapat diamati."
    },
    {
      "seq_in_article": 114,
      "pinyin": "rén wù shén lì zāi hài hé xiū fù xíng dòng cháng bèi fàng zài tóng yí duàn xù shì lǐ xíng chéng qiáng liè huà miàn",
      "content_zh": "人物、神力、灾害和修复行动常被放在同一段叙事里，形成强烈画面。",
      "content_en": "Figures, divine power, disasters, and repair actions often appear together and create vivid images.",
      "content_vi": "Những thay đổi nhỏ trong đời thường thường cho thấy cách xã hội vận hành.",
      "content_th": "การเปลี่ยนเล็กๆ ในชีวิตประจำวันมักเผยให้เห็นวิธีที่สังคมทำงาน",
      "content_id": "Perubahan kecil dalam keseharian sering memperlihatkan cara masyarakat bekerja."
    },
    {
      "seq_in_article": 115,
      "pinyin": "rú guǒ zhī jì zhù míng zì rén men róng yì hū lüè gù shì bèi hòu de zì rán guān chá hé shēng huó yuàn wàng",
      "content_zh": "如果只记住名字，人们容易忽略故事背后的自然观察和生活愿望。",
      "content_en": "If people only remember names, they may miss the natural observation and life wishes behind the stories.",
      "content_vi": "Nếu chỉ nhớ tên gọi, người học dễ bỏ qua bối cảnh và cách dùng cụ thể.",
      "content_th": "หากจำเพียงชื่อ ผู้เรียนอาจมองข้ามบริบทและวิธีใช้ที่เฉพาะเจาะจง",
      "content_id": "Jika hanya mengingat nama, pelajar mudah melewatkan konteks dan cara pakai konkret."
    },
    {
      "seq_in_article": 116,
      "pinyin": "xué xí qù wèi yě shuō míng shén huà cháng yòng kuā zhāng xíng xiàng huí dá qǐ yuán zhì xù hé shēng cún wèn tí",
      "content_zh": "学习趣味也说明，神话常用夸张形象回答起源、秩序和生存问题。",
      "content_en": "learning interest also shows how myths use exaggerated images to answer questions of origin, order, and survival.",
      "content_vi": "Điều đó cho thấy Thương Hiệt tạo chữ và nguồn gốc chữ viết được hình thành từ nhiều lớp kinh nghiệm lâu dài.",
      "content_th": "สิ่งนี้แสดงว่าชางเจี๋ยสร้างอักษรกับต้นกำเนิดตัวเขียนเกิดจากประสบการณ์ยาวนานหลายชั้น",
      "content_id": "Hal ini menunjukkan bahwa Cangjie mencipta aksara dan asal tulisan dibentuk oleh banyak lapisan pengalaman panjang."
    },
    {
      "seq_in_article": 117,
      "pinyin": "zhè xiē gù shì tōng guò kǒu tóu jiǎng shù tú xiàng jié rì hé ér tóng dú wù bú duàn liú chuán",
      "content_zh": "这些故事通过口头讲述、图像、节日和儿童读物不断流传。",
      "content_en": "These stories continue through oral telling, images, festivals, and children’s books.",
      "content_vi": "Nội dung này tiếp tục truyền qua lớp học, truyền thông, gia đình và quan sát hằng ngày.",
      "content_th": "เนื้อหานี้ยังส่งต่อผ่านห้องเรียน สื่อ ครอบครัว และการสังเกตประจำวัน",
      "content_id": "Isi ini terus diwariskan melalui kelas, media, keluarga, dan pengamatan harian."
    },
    {
      "seq_in_article": 118,
      "pinyin": "dāng dài lǐ jiě shén huà shí kě yǐ tóng shí kàn dào xiǎng xiàng lì xiàng zhēng yì yì hé wén huà jì yì",
      "content_zh": "当代理解神话时，可以同时看到想象力、象征意义和文化记忆。",
      "content_en": "Modern understanding of myth can see imagination, symbolism, and cultural memory at the same time.",
      "content_vi": "Trong đời sống hiện đại, cần hiểu nghĩa cũ rồi so sánh với tình huống mới.",
      "content_th": "ในชีวิตสมัยใหม่ ควรเข้าใจความหมายเดิมแล้วเปรียบกับสถานการณ์ใหม่",
      "content_id": "Dalam kehidupan modern, makna lama perlu dipahami lalu dibandingkan dengan keadaan baru."
    },
    {
      "seq_in_article": 119,
      "pinyin": "bǎ jué sè qíng jié hé jiě shì gōng néng lián qǐ lái shén huà jiù bù zhǐ shì qí yì gù shì",
      "content_zh": "把角色、情节和解释功能连起来，神话就不只是奇异故事。",
      "content_en": "When roles, plots, and explanatory functions are connected, myths are more than strange tales.",
      "content_vi": "Khi đặt hình ảnh, hành động và ý nghĩa cạnh nhau, truyền thống trở nên gần hơn.",
      "content_th": "เมื่อนำภาพ การกระทำ และความหมายมาไว้ด้วยกัน ประเพณีจะใกล้ตัวขึ้น",
      "content_id": "Ketika gambar, tindakan, dan makna ditempatkan bersama, tradisi menjadi lebih dekat."
    },
    {
      "seq_in_article": 120,
      "pinyin": "yīn cǐ xué xí qù wèi bù jǐn shì chuán shuō nèi róng yě bāng zhù rén men lǐ jiě cāng jié zào zì hé wén zì qǐ yuán",
      "content_zh": "因此，学习趣味不仅是传说内容，也帮助人们理解仓颉造字和文字起源。",
      "content_en": "Therefore, learning interest is not only legend content but also a way to understand Cangjie creating characters and writing origins.",
      "content_vi": "Vì vậy, nội dung này giúp người học hôm nay hiểu Thương Hiệt tạo chữ và nguồn gốc chữ viết rõ hơn.",
      "content_th": "ดังนั้นเนื้อหานี้ช่วยให้ผู้เรียนวันนี้เข้าใจชางเจี๋ยสร้างอักษรกับต้นกำเนิดตัวเขียนได้ชัดเจนขึ้น",
      "content_id": "Karena itu, bagian ini membantu pelajar masa kini memahami Cangjie mencipta aksara dan asal tulisan dengan lebih jelas."
    }
  ]
}
